<?xml version="1.0" encoding="utf-8"?>
<Return xmlns="http://www.irs.gov/efile" xmlns:xsi="http://www.w3.org/2001/XMLSchema-instance" xsi:schemaLocation="http://www.irs.gov/efile" returnVersion="2022v5.0">
  <ReturnHeader binaryAttachmentCnt="0">
    <ReturnTs>2023-03-20T14:12:06-05:00</ReturnTs>
    <TaxPeriodEndDt>2022-12-31</TaxPeriodEndDt>
    <PreparerFirmGrp>
      <PreparerFirmEIN>810348775</PreparerFirmEIN>
      <PreparerFirmName>
        <BusinessNameLine1Txt>JUNKERMIERCLARKCAMPANELLASTEVENS PC</BusinessNameLine1Txt>
      </PreparerFirmName>
      <PreparerUSAddress>
        <AddressLine1Txt>321 W BROADWAY 4TH FLOOR</AddressLine1Txt>
        <CityNm>MISSOULA</CityNm>
        <StateAbbreviationCd>MT</StateAbbreviationCd>
        <ZIPCd>59802</ZIPCd>
      </PreparerUSAddress>
    </PreparerFirmGrp>
    <ReturnTypeCd>990EZ</ReturnTypeCd>
    <TaxPeriodBeginDt>2022-01-01</TaxPeriodBeginDt>
    <Filer>
      <EIN>810416133</EIN>
      <BusinessName>
        <BusinessNameLine1Txt>LOLO COMMUNITY CLUB</BusinessNameLine1Txt>
      </BusinessName>
      <BusinessNameControlTxt>LOLO</BusinessNameControlTxt>
      <PhoneNum>4065442538</PhoneNum>
      <USAddress>
        <AddressLine1Txt>PO BOX 462</AddressLine1Txt>
        <CityNm>LOLO</CityNm>
        <StateAbbreviationCd>MT</StateAbbreviationCd>
        <ZIPCd>59847</ZIPCd>
      </USAddress>
    </Filer>
    <BusinessOfficerGrp>
      <PersonNm>EILEEN NELSON</PersonNm>
      <PersonTitleTxt>PRESIDENT</PersonTitleTxt>
      <PhoneNum>4065442538</PhoneNum>
      <SignatureDt>2023-03-20</SignatureDt>
      <DiscussWithPaidPreparerInd>1</DiscussWithPaidPreparerInd>
    </BusinessOfficerGrp>
    <SigningOfficerGrp>
      <PersonFullName>
        <PersonFirstNm>EILEEN</PersonFirstNm>
        <PersonLastNm>NELSON</PersonLastNm>
      </PersonFullName>
      <SSN>999009999</SSN>
    </SigningOfficerGrp>
    <IRSResponsiblePrtyInfoCurrInd>0</IRSResponsiblePrtyInfoCurrInd>
    <PreparerPersonGrp>
      <PreparerPersonNm>DREW RIEKER CPAABV</PreparerPersonNm>
      <PTIN>P01372762</PTIN>
      <PhoneNum>4065494148</PhoneNum>
    </PreparerPersonGrp>
    <AdditionalFilerInformation>
      <TrustedCustomerGrp>
        <TrustedCustomerCd>2</TrustedCustomerCd>
        <AuthenticationAssuranceLevelCd>AAL1</AuthenticationAssuranceLevelCd>
        <IdentityAssuranceLevelCd>IAL1</IdentityAssuranceLevelCd>
      </TrustedCustomerGrp>
    </AdditionalFilerInformation>
    <TaxYr>2022</TaxYr>
    <BuildTS>2023-04-26 12:10:37Z</BuildTS>
  </ReturnHeader>
  <ReturnData documentCnt="6">
    <IRS990EZ documentId="RetDoc1234200001" referenceDocumentId="RetDoc1051800001 RetDoc2278000001">
      <MethodOfAccountingCashInd>X</MethodOfAccountingCashInd>
      <WebsiteAddressTxt>WWW.LOLOCOMMUNITYCENTER.COM</WebsiteAddressTxt>
      <Organization501c3Ind referenceDocumentId="RetDoc1039100001">X</Organization501c3Ind>
      <TypeOfOrganizationCorpInd>X</TypeOfOrganizationCorpInd>
      <GrossReceiptsAmt>163058</GrossReceiptsAmt>
      <InfoInScheduleOPartIInd>X</InfoInScheduleOPartIInd>
      <ContributionsGiftsGrantsEtcAmt>30570</ContributionsGiftsGrantsEtcAmt>
      <ProgramServiceRevenueAmt>21020</ProgramServiceRevenueAmt>
      <MembershipDuesAmt>1996</MembershipDuesAmt>
      <GamingGrossIncomeAmt referenceDocumentId="RetDoc1041300001">109472</GamingGrossIncomeAmt>
      <SpecialEventsDirectExpensesAmt>86843</SpecialEventsDirectExpensesAmt>
      <SpecialEventsNetIncomeLossAmt>22629</SpecialEventsNetIncomeLossAmt>
      <TotalRevenueAmt>76215</TotalRevenueAmt>
      <OccupancyRentUtltsAndMaintAmt>45715</OccupancyRentUtltsAndMaintAmt>
      <OtherExpensesTotalAmt>16139</OtherExpensesTotalAmt>
      <TotalExpensesAmt>61854</TotalExpensesAmt>
      <ExcessOrDeficitForYearAmt>14361</ExcessOrDeficitForYearAmt>
      <NetAssetsOrFundBalancesBOYAmt>91868</NetAssetsOrFundBalancesBOYAmt>
      <OtherChangesInNetAssetsAmt>0</OtherChangesInNetAssetsAmt>
      <NetAssetsOrFundBalancesEOYAmt>106229</NetAssetsOrFundBalancesEOYAmt>
      <InfoInScheduleOPartIIInd>X</InfoInScheduleOPartIIInd>
      <CashSavingsAndInvestmentsGrp>
        <BOYAmt>91063</BOYAmt>
        <EOYAmt>105424</EOYAmt>
      </CashSavingsAndInvestmentsGrp>
      <OtherAssetsTotalDetail>
        <BOYAmt>805</BOYAmt>
        <EOYAmt>805</EOYAmt>
      </OtherAssetsTotalDetail>
      <Form990TotalAssetsGrp>
        <BOYAmt>91868</BOYAmt>
        <EOYAmt>106229</EOYAmt>
      </Form990TotalAssetsGrp>
      <SumOfTotalLiabilitiesGrp>
        <BOYAmt>0</BOYAmt>
        <EOYAmt>0</EOYAmt>
      </SumOfTotalLiabilitiesGrp>
      <NetAssetsOrFundBalancesGrp>
        <BOYAmt>91868</BOYAmt>
        <EOYAmt>106229</EOYAmt>
      </NetAssetsOrFundBalancesGrp>
      <InfoInScheduleOPartIIIInd>X</InfoInScheduleOPartIIIInd>
      <PrimaryExemptPurposeTxt>TO BUILD COMMUNITY BY PROVIDING A SOCIAL AND RECREATIONAL SPACE FOR THE RESIDENTS OF LOLO, MONTANA AND SURROUNDING AREAS.</PrimaryExemptPurposeTxt>
      <ProgramSrvcAccomplishmentGrp>
        <DescriptionProgramSrvcAccomTxt>THE LOLO COMMUNITY CLUB (LCC) HOSTED A NUMBER OF COMMUNITY EVENTS THAT WERE FREE TO THE PUBLIC. THIS INCLUDED A SAFE HALLOWEEN EVENT CALLED "TRUNK OR TREAT" WHERE LOLO RESIDENTS DECORATED THEIR VEHICLES AND PASSED OUT CANDY TO LOCAL YOUTH. IN DECEMBER, THE LCC HOSTED ITS 6TH ANNUAL TREE LIGHTING EVENT PROVIDING GAMES, SNACKS, MUSIC, HAYRIDES, AND A VISIT FROM SANTA. SURPRISE GUEST: THE GRINCH. WE ALSO ORGANIZED AND RAN AN EVENT CALLED "THE GREAT LIGHT FIGHT" IN OUR COMMUNITY. THIS EVENT ENCOURAGED FRIENDLY COMPETITION AMONG NEIGHBORS TO DECORATE THEIR HOMES DURING THE HOLIDAY SEASON. DURING THE SUMMER, THE COMMUNITY CENTER WAS ALSO HOST TO A DAY CAMP FOR LOCAL CHILDREN THAT WAS RUN BY THE LOLO PRESCHOOL. THE LCC ALSO SPONSORED TWO CRAFT FAIRS, GIVING LOCAL VENDERS A CHANCE TO SELL THEIR GOODS IN THE COMMUNITY. IN JUNE THE CENTER HOSTED THE BITTERROOT 50 MILE GARAGE SALE. A SMALL FARMERS MARKET WAS HELD DURING MAY-JUNE. THE LOLO COMMUNITY CLUB ALSO IS THE LOCATION OF THE LOLO FOOD BANK WHICH IS A SATELLITE OF THE MISSOULA FOOD BANK. FOOD IS DISTRIBUTED TO THOSE IN NEED TWICE PER MONTH. WE SERVE AN AVERAGE OF 25-50 FAMILIES. IN ADDITION, WE ALSO HELP FACILITATE AND RUN A HOLIDAY MEAL DRIVE FOR BOTH THANKSGIVING AND CHRISTMAS. MISSOULA AGING SERVICES IS WORKING WITH THE COMMUNITY CENTER AND THE LOLO SENIOR CITIZENS WEEKLY LUNCH GROUP. THIS GROUP NOW MEETS ONCE A WEEK FOR LUNCH AT THE CENTER. MEALS ARE PREPARED AND PROVIDED BY LOLO SCHOOL KITCHEN STAFF. WE SUPPORT YOUTH SPORTS BY PROVIDING A HOME FOR THE NORTH BITTERROOT LITTLE LEAGUE THROUGH THE USE OF SIX BALL FIELDS THAT ARE ON OUR PROPERTY. MANY OF THE LOCAL YOUTH SOFTBALL TEAMS PRACTICE ON OUR FIELDS AS WELL. WE WORKED WITH THE RED CROSS TO HOLD FOUR BLOOD DRIVES AT THE LOLO COMMUNITY CENTER. OTHER COMMUNITY EVENTS INCLUDED USE OF OUR FACILITIES BY WOODMAN SCHOOL FOR A PRODUCTION OF A PLAY BY THE MONTANA CHILDREN'S THEATRE. FINALLY, OUR FACILITY IS IN USE ALMOST EVERY EVENING AND A NUMBER OF WEEKENDS BY A VARIETY OF NONPROFITS AND OTHER ORGANIZATION FOR THEIR MEETINGS AND EDUCATIONAL PROGRAMS.</DescriptionProgramSrvcAccomTxt>
        <GrantsAndAllocationsAmt>0</GrantsAndAllocationsAmt>
        <ProgramServiceExpensesAmt>7651</ProgramServiceExpensesAmt>
      </ProgramSrvcAccomplishmentGrp>
      <TotalProgramServiceExpensesAmt>7651</TotalProgramServiceExpensesAmt>
      <OfficerDirectorTrusteeEmplGrp>
        <PersonNm>EILEEN NELSON</PersonNm>
        <TitleTxt>PRESIDENT</TitleTxt>
        <AverageHrsPerWkDevotedToPosRt>20.00</AverageHrsPerWkDevotedToPosRt>
        <CompensationAmt>0</CompensationAmt>
        <EmployeeBenefitProgramAmt>0</EmployeeBenefitProgramAmt>
        <ExpenseAccountOtherAllwncAmt>0</ExpenseAccountOtherAllwncAmt>
      </OfficerDirectorTrusteeEmplGrp>
      <OfficerDirectorTrusteeEmplGrp>
        <PersonNm>LOUANN HANSEN</PersonNm>
        <TitleTxt>VICE PRESIDENT (FORMER)</TitleTxt>
        <AverageHrsPerWkDevotedToPosRt>5.00</AverageHrsPerWkDevotedToPosRt>
        <CompensationAmt>0</CompensationAmt>
        <EmployeeBenefitProgramAmt>0</EmployeeBenefitProgramAmt>
        <ExpenseAccountOtherAllwncAmt>0</ExpenseAccountOtherAllwncAmt>
      </OfficerDirectorTrusteeEmplGrp>
      <OfficerDirectorTrusteeEmplGrp>
        <PersonNm>KORRIE BUTLER</PersonNm>
        <TitleTxt>SECRETARY</TitleTxt>
        <AverageHrsPerWkDevotedToPosRt>10.00</AverageHrsPerWkDevotedToPosRt>
        <CompensationAmt>0</CompensationAmt>
        <EmployeeBenefitProgramAmt>0</EmployeeBenefitProgramAmt>
        <ExpenseAccountOtherAllwncAmt>0</ExpenseAccountOtherAllwncAmt>
      </OfficerDirectorTrusteeEmplGrp>
      <OfficerDirectorTrusteeEmplGrp>
        <PersonNm>DONALD SAX</PersonNm>
        <TitleTxt>TREASURER (FORMER)</TitleTxt>
        <AverageHrsPerWkDevotedToPosRt>10.00</AverageHrsPerWkDevotedToPosRt>
        <CompensationAmt>0</CompensationAmt>
        <EmployeeBenefitProgramAmt>0</EmployeeBenefitProgramAmt>
        <ExpenseAccountOtherAllwncAmt>0</ExpenseAccountOtherAllwncAmt>
      </OfficerDirectorTrusteeEmplGrp>
      <OfficerDirectorTrusteeEmplGrp>
        <PersonNm>CORTNEY HANSEN</PersonNm>
        <TitleTxt>BOARD MEMBER</TitleTxt>
        <AverageHrsPerWkDevotedToPosRt>7.00</AverageHrsPerWkDevotedToPosRt>
        <CompensationAmt>0</CompensationAmt>
        <EmployeeBenefitProgramAmt>0</EmployeeBenefitProgramAmt>
        <ExpenseAccountOtherAllwncAmt>0</ExpenseAccountOtherAllwncAmt>
      </OfficerDirectorTrusteeEmplGrp>
      <OfficerDirectorTrusteeEmplGrp>
        <PersonNm>JAMIE BALLAS</PersonNm>
        <TitleTxt>BOARD MEMBER (FORMER)</TitleTxt>
        <AverageHrsPerWkDevotedToPosRt>0.50</AverageHrsPerWkDevotedToPosRt>
        <CompensationAmt>0</CompensationAmt>
        <EmployeeBenefitProgramAmt>0</EmployeeBenefitProgramAmt>
        <ExpenseAccountOtherAllwncAmt>0</ExpenseAccountOtherAllwncAmt>
      </OfficerDirectorTrusteeEmplGrp>
      <OfficerDirectorTrusteeEmplGrp>
        <PersonNm>ROBIN KEITH</PersonNm>
        <TitleTxt>AT LARGE (FORMER)</TitleTxt>
        <AverageHrsPerWkDevotedToPosRt>4.00</AverageHrsPerWkDevotedToPosRt>
        <CompensationAmt>0</CompensationAmt>
        <EmployeeBenefitProgramAmt>0</EmployeeBenefitProgramAmt>
        <ExpenseAccountOtherAllwncAmt>0</ExpenseAccountOtherAllwncAmt>
      </OfficerDirectorTrusteeEmplGrp>
      <InfoInScheduleOPartVInd>X</InfoInScheduleOPartVInd>
      <ActivitiesNotPreviouslyRptInd>0</ActivitiesNotPreviouslyRptInd>
      <ChgMadeToOrgnzngDocNotRptInd>0</ChgMadeToOrgnzngDocNotRptInd>
      <OrganizationHadUBIInd>0</OrganizationHadUBIInd>
      <SubjectToProxyTaxInd>0</SubjectToProxyTaxInd>
      <OrganizationDissolvedEtcInd>0</OrganizationDissolvedEtcInd>
      <DirectIndirectPltclExpendAmt>0</DirectIndirectPltclExpendAmt>
      <MadeLoansToFromOfficersInd>0</MadeLoansToFromOfficersInd>
      <TaxImposedUnderIRC4911Amt>0</TaxImposedUnderIRC4911Amt>
      <TaxImposedUnderIRC4912Amt>0</TaxImposedUnderIRC4912Amt>
      <TaxImposedUnderIRC4955Amt>0</TaxImposedUnderIRC4955Amt>
      <EngagedInExcessBenefitTransInd>0</EngagedInExcessBenefitTransInd>
      <TaxImposedOnOrganizationMgrAmt>0</TaxImposedOnOrganizationMgrAmt>
      <TaxReimbursedByOrganizationAmt>0</TaxReimbursedByOrganizationAmt>
      <ProhibitedTaxShelterTransInd>0</ProhibitedTaxShelterTransInd>
      <BooksInCareOfDetail>
        <BusinessName>
          <BusinessNameLine1Txt>THE ORGANIZATION</BusinessNameLine1Txt>
        </BusinessName>
        <USAddress>
          <AddressLine1Txt>PO BOX 462</AddressLine1Txt>
          <CityNm>LOLO</CityNm>
          <StateAbbreviationCd>MT</StateAbbreviationCd>
          <ZIPCd>59847</ZIPCd>
        </USAddress>
        <PhoneNum>4065442538</PhoneNum>
      </BooksInCareOfDetail>
      <ForeignFinancialAccountInd>0</ForeignFinancialAccountInd>
      <ForeignOfficeInd>0</ForeignOfficeInd>
      <DonorAdvisedFndsInd>0</DonorAdvisedFndsInd>
      <OperateHospitalInd>0</OperateHospitalInd>
      <TanningServicesProvidedInd>0</TanningServicesProvidedInd>
      <RelatedOrganizationCtrlEntInd>0</RelatedOrganizationCtrlEntInd>
      <PoliticalCampaignActyInd>0</PoliticalCampaignActyInd>
      <LobbyingActivitiesInd>0</LobbyingActivitiesInd>
      <SchoolOperatingInd>0</SchoolOperatingInd>
      <TrnsfrExmptNonChrtblRltdOrgInd>0</TrnsfrExmptNonChrtblRltdOrgInd>
      <PartVIOfCompOfHghstPdEmplTxt>NONE</PartVIOfCompOfHghstPdEmplTxt>
      <PartVIHghstPdCntrctProfSrvcTxt>NONE</PartVIHghstPdCntrctProfSrvcTxt>
      <FiledScheduleAInd>1</FiledScheduleAInd>
    </IRS990EZ>
    <IRS990ScheduleA documentId="RetDoc1039100001">
      <PublicOrganization170Ind>X</PublicOrganization170Ind>
      <GiftsGrantsContriRcvd170Grp>
        <CurrentTaxYearMinus1YearAmt>40820</CurrentTaxYearMinus1YearAmt>
        <CurrentTaxYearAmt>32566</CurrentTaxYearAmt>
        <TotalAmt>73386</TotalAmt>
      </GiftsGrantsContriRcvd170Grp>
      <TotalCalendarYear170Grp>
        <CurrentTaxYearMinus1YearAmt>40820</CurrentTaxYearMinus1YearAmt>
        <CurrentTaxYearAmt>32566</CurrentTaxYearAmt>
        <TotalAmt>73386</TotalAmt>
      </TotalCalendarYear170Grp>
      <PublicSupportTotal170Amt>73386</PublicSupportTotal170Amt>
      <TotalSupportAmt>73386</TotalSupportAmt>
      <GrossReceiptsRltdActivitiesAmt>41430</GrossReceiptsRltdActivitiesAmt>
      <First5Years170Ind>X</First5Years170Ind>
    </IRS990ScheduleA>
    <IRS990ScheduleB documentId="RetDoc1234500001">
      <ContributorInformationGrp>
        <ContributorNum>RESTRICTED</ContributorNum>
        <ContributorBusinessName>
          <BusinessNameLine1>RESTRICTED</BusinessNameLine1>
        </ContributorBusinessName>
        <ContributorUSAddress>
          <AddressLine1>RESTRICTED</AddressLine1>
          <AddressLine2>RESTRICTED</AddressLine2>
          <City>RESTRICTED</City>
          <State>RESTRICTED</State>
          <ZIPCode>RESTRICTED</ZIPCode>
        </ContributorUSAddress>
        <TotalContributionsAmt>RESTRICTED</TotalContributionsAmt>
      </ContributorInformationGrp>
    </IRS990ScheduleB>
    <IRS990ScheduleG documentId="RetDoc1041300001">
      <GamingInformationGrp>
        <GrossRevenueBingoAmt>98239</GrossRevenueBingoAmt>
        <CashPrizesBingoAmt>78798</CashPrizesBingoAmt>
        <OtherDirectExpensesBingoAmt>4517</OtherDirectExpensesBingoAmt>
        <VolunteerLaborBingoInd>1</VolunteerLaborBingoInd>
        <VolunteerLaborBingoPct>1.00000</VolunteerLaborBingoPct>
        <GrossRevenueOtherGamingAmt>11233</GrossRevenueOtherGamingAmt>
        <CashPrizesOtherGamingAmt>3528</CashPrizesOtherGamingAmt>
        <OthDirectExpnssOtherGamingAmt>0</OthDirectExpnssOtherGamingAmt>
        <VolunteerLaborOtherGamingInd>1</VolunteerLaborOtherGamingInd>
        <VolunteerLaborOtherGamingPct>1.00000</VolunteerLaborOtherGamingPct>
        <GrossRevenueTotalGamingAmt>109472</GrossRevenueTotalGamingAmt>
        <CashPrizesTotalGamingAmt>82326</CashPrizesTotalGamingAmt>
        <OthDirectExpnssTotalGamingAmt>4517</OthDirectExpnssTotalGamingAmt>
        <DirectExpenseSummaryGamingAmt>86843</DirectExpenseSummaryGamingAmt>
        <NetGamingIncomeSummaryAmt>22629</NetGamingIncomeSummaryAmt>
      </GamingInformationGrp>
      <StatesWhereGamingConductedCd>MT</StatesWhereGamingConductedCd>
      <LicensedInd>1</LicensedInd>
      <LicenseSuspendedEtcInd>0</LicenseSuspendedEtcInd>
      <GamingWithNonmembersInd>0</GamingWithNonmembersInd>
      <MemberOfOtherEntityInd>0</MemberOfOtherEntityInd>
      <IndividualWithBooksNm>EILEEN NELSON</IndividualWithBooksNm>
      <PersonsWithBooksUSAddress>
        <AddressLine1Txt>PO BOX 462</AddressLine1Txt>
        <CityNm>LOLO</CityNm>
        <StateAbbreviationCd>MT</StateAbbreviationCd>
        <ZIPCd>59847</ZIPCd>
      </PersonsWithBooksUSAddress>
      <CntrctWith3rdPrtyForGameRevInd>0</CntrctWith3rdPrtyForGameRevInd>
      <CharitableDistributionRqrInd>0</CharitableDistributionRqrInd>
    </IRS990ScheduleG>
    <IRS990ScheduleO documentId="RetDoc1051800001">
      <SupplementalInformationDetail>
        <FormAndLineReferenceDesc>FORM 990-EZ, PART I, LINE 16 - OTHER EXPENSES</FormAndLineReferenceDesc>
        <ExplanationTxt>DESCRIPTION: ADVERTISING. AMOUNT: 100. DESCRIPTION: OFFICE SUPPLIES. AMOUNT: 297. DESCRIPTION: TAXES AND LICENSES. AMOUNT: 119. DESCRIPTION: INSPECTIONS AND TESTS. AMOUNT: 121. DESCRIPTION: INSURANCE. AMOUNT: 6,249. DESCRIPTION: SECURITY SYSTEM. AMOUNT: 755. DESCRIPTION: PROGRAM EXPENSES. AMOUNT: 7,651. DESCRIPTION: JANITORIAL SUPPLIES. AMOUNT: 847. TOTAL TO FORM 990-EZ, LINE 16: 16,139.</ExplanationTxt>
      </SupplementalInformationDetail>
      <SupplementalInformationDetail>
        <FormAndLineReferenceDesc>FORM 990-EZ, PART II, LINE 24 - OTHER ASSETS</FormAndLineReferenceDesc>
        <ExplanationTxt>DESCRIPTION: GIFD CARDS. BEG. OF YEAR AMOUNT: 805. END OF YEAR AMOUNT: 805.</ExplanationTxt>
      </SupplementalInformationDetail>
    </IRS990ScheduleO>
    <TransferPrsnlBnftContractsDecl documentId="RetDoc2278000001">
      <DeclarationDesc>THE ORGANIZATION DID NOT, DURING THE YEAR, RECEIVE ANY FUNDS, DIRECTLY,OR INDIRECTLY, TO PAY PREMIUMS ON A PERSONAL BENEFIT CONTRACT.THE ORGANIZATION, DID NOT, DURING THE YEAR, PAY ANY PREMIUMS, DIRECTLY,OR INDIRECTLY, ON A PERSONAL BENEFIT CONTRACT.</DeclarationDesc>
    </TransferPrsnlBnftContractsDecl>
  </ReturnData>
</Return>
