<?xml version="1.0" encoding="utf-8"?>
<Return returnVersion="2022v4.1" xmlns="http://www.irs.gov/efile" xsi:schemaLocation="http://www.irs.gov/efile" xmlns:xsi="http://www.w3.org/2001/XMLSchema-instance">
  <ReturnHeader binaryAttachmentCnt="0">
    <ReturnTs>2023-03-15T15:50:51-05:00</ReturnTs>
    <TaxPeriodEndDt>2022-12-31</TaxPeriodEndDt>
    <PreparerFirmGrp>
      <PreparerFirmEIN>272129276</PreparerFirmEIN>
      <PreparerFirmName>
        <BusinessNameLine1Txt>GEMINI BUSINESS SOLUTIONS</BusinessNameLine1Txt>
      </PreparerFirmName>
      <PreparerUSAddress>
        <AddressLine1Txt>8530 TIDWELL ROAD</AddressLine1Txt>
        <CityNm>HOUSTON</CityNm>
        <StateAbbreviationCd>TX</StateAbbreviationCd>
        <ZIPCd>77028</ZIPCd>
      </PreparerUSAddress>
    </PreparerFirmGrp>
    <ReturnTypeCd>990EZ</ReturnTypeCd>
    <TaxPeriodBeginDt>2022-01-01</TaxPeriodBeginDt>
    <Filer>
      <EIN>680579201</EIN>
      <BusinessName>
        <BusinessNameLine1Txt>KRAYOLA KIDZ INC</BusinessNameLine1Txt>
      </BusinessName>
      <BusinessNameControlTxt>KRAY</BusinessNameControlTxt>
      <PhoneNum>8325660335</PhoneNum>
      <USAddress>
        <AddressLine1Txt>2200 SPEARS ROAD</AddressLine1Txt>
        <CityNm>HOUSTON</CityNm>
        <StateAbbreviationCd>TX</StateAbbreviationCd>
        <ZIPCd>77067</ZIPCd>
      </USAddress>
    </Filer>
    <BusinessOfficerGrp>
      <PersonNm>LAURETTA MAIDEN</PersonNm>
      <PersonTitleTxt>ACCOUNTANT</PersonTitleTxt>
      <PhoneNum>7136358366</PhoneNum>
      <SignatureDt>2023-03-07</SignatureDt>
    </BusinessOfficerGrp>
    <SigningOfficerGrp>
      <PersonFullName>
        <PersonFirstNm>LAURETTA</PersonFirstNm>
        <PersonLastNm>MAIDEN</PersonLastNm>
      </PersonFullName>
      <SSN>XXX-XX-XXXX</SSN>
    </SigningOfficerGrp>
    <IRSResponsiblePrtyInfoCurrInd>0</IRSResponsiblePrtyInfoCurrInd>
    <PreparerPersonGrp>
      <PreparerPersonNm>LAURETTA MAIDEN</PreparerPersonNm>
      <PTIN>P01086699</PTIN>
      <PhoneNum>7136358366</PhoneNum>
    </PreparerPersonGrp>
    <TaxYr>2022</TaxYr>
    <BuildTS>2023-04-26 12:10:37Z</BuildTS>
  </ReturnHeader>
  <ReturnData documentCnt="2">
    <IRS990EZ documentId="IRS990EZ">
      <ScheduleBNotRequiredInd>X</ScheduleBNotRequiredInd>
      <Organization501c3Ind referenceDocumentId="IRS990ScheduleA">X</Organization501c3Ind>
      <TypeOfOrganizationCorpInd>X</TypeOfOrganizationCorpInd>
      <GrossReceiptsAmt>43090</GrossReceiptsAmt>
      <ContributionsGiftsGrantsEtcAmt>43090</ContributionsGiftsGrantsEtcAmt>
      <TotalRevenueAmt>43090</TotalRevenueAmt>
      <OccupancyRentUtltsAndMaintAmt>43090</OccupancyRentUtltsAndMaintAmt>
      <TotalExpensesAmt>43090</TotalExpensesAmt>
      <Form990TotalAssetsGrp>
        <BOYAmt>0</BOYAmt>
        <EOYAmt>0</EOYAmt>
      </Form990TotalAssetsGrp>
      <NetAssetsOrFundBalancesGrp>
        <BOYAmt>0</BOYAmt>
        <EOYAmt>0</EOYAmt>
      </NetAssetsOrFundBalancesGrp>
      <PrimaryExemptPurposeTxt>TO PROVIDE QUAILTY CHILDCARE FOR THE UNDER PRIVILIDGED</PrimaryExemptPurposeTxt>
      <ProgramSrvcAccomplishmentGrp>
        <DescriptionProgramSrvcAccomTxt>N/A</DescriptionProgramSrvcAccomTxt>
        <GrantsAndAllocationsAmt>43090</GrantsAndAllocationsAmt>
        <ProgramServiceExpensesAmt>43090</ProgramServiceExpensesAmt>
      </ProgramSrvcAccomplishmentGrp>
      <TotalProgramServiceExpensesAmt>43090</TotalProgramServiceExpensesAmt>
      <OfficerDirectorTrusteeEmplGrp>
        <PersonNm>FRANCINE EDWARDS</PersonNm>
        <TitleTxt>PRESIDENT</TitleTxt>
        <AverageHrsPerWkDevotedToPosRt>25</AverageHrsPerWkDevotedToPosRt>
        <CompensationAmt>0</CompensationAmt>
        <EmployeeBenefitProgramAmt>0</EmployeeBenefitProgramAmt>
        <ExpenseAccountOtherAllwncAmt>0</ExpenseAccountOtherAllwncAmt>
      </OfficerDirectorTrusteeEmplGrp>
      <OfficerDirectorTrusteeEmplGrp>
        <PersonNm>JENNIFER CLAY</PersonNm>
        <TitleTxt>SECRETARY</TitleTxt>
        <AverageHrsPerWkDevotedToPosRt>10</AverageHrsPerWkDevotedToPosRt>
        <CompensationAmt>0</CompensationAmt>
        <EmployeeBenefitProgramAmt>0</EmployeeBenefitProgramAmt>
        <ExpenseAccountOtherAllwncAmt>0</ExpenseAccountOtherAllwncAmt>
      </OfficerDirectorTrusteeEmplGrp>
      <OfficerDirectorTrusteeEmplGrp>
        <PersonNm>NIKTA HICKMAN</PersonNm>
        <TitleTxt>TREASURER</TitleTxt>
        <AverageHrsPerWkDevotedToPosRt>10</AverageHrsPerWkDevotedToPosRt>
        <CompensationAmt>0</CompensationAmt>
        <EmployeeBenefitProgramAmt>0</EmployeeBenefitProgramAmt>
        <ExpenseAccountOtherAllwncAmt>0</ExpenseAccountOtherAllwncAmt>
      </OfficerDirectorTrusteeEmplGrp>
      <ActivitiesNotPreviouslyRptInd>0</ActivitiesNotPreviouslyRptInd>
      <ChgMadeToOrgnzngDocNotRptInd>0</ChgMadeToOrgnzngDocNotRptInd>
      <OrganizationHadUBIInd>0</OrganizationHadUBIInd>
      <SubjectToProxyTaxInd>0</SubjectToProxyTaxInd>
      <OrganizationDissolvedEtcInd>0</OrganizationDissolvedEtcInd>
      <Form1120PolFiledInd>0</Form1120PolFiledInd>
      <MadeLoansToFromOfficersInd>0</MadeLoansToFromOfficersInd>
      <EngagedInExcessBenefitTransInd>0</EngagedInExcessBenefitTransInd>
      <ProhibitedTaxShelterTransInd>0</ProhibitedTaxShelterTransInd>
      <BooksInCareOfDetail>
        <PersonNm>FRANCINE EDWARDS</PersonNm>
        <USAddress>
          <AddressLine1Txt>2200 SPEARS ROAD</AddressLine1Txt>
          <CityNm>HOUSTON</CityNm>
          <StateAbbreviationCd>TX</StateAbbreviationCd>
          <ZIPCd>77067</ZIPCd>
        </USAddress>
        <PhoneNum>8325660335</PhoneNum>
      </BooksInCareOfDetail>
      <ForeignFinancialAccountInd>0</ForeignFinancialAccountInd>
      <ForeignOfficeInd>0</ForeignOfficeInd>
      <DonorAdvisedFndsInd>0</DonorAdvisedFndsInd>
      <OperateHospitalInd>0</OperateHospitalInd>
      <TanningServicesProvidedInd>0</TanningServicesProvidedInd>
      <Form720FiledInd>0</Form720FiledInd>
      <RelatedOrganizationCtrlEntInd>0</RelatedOrganizationCtrlEntInd>
      <TransactionWithControlEntInd>0</TransactionWithControlEntInd>
      <PoliticalCampaignActyInd>0</PoliticalCampaignActyInd>
      <LobbyingActivitiesInd>0</LobbyingActivitiesInd>
      <SchoolOperatingInd>0</SchoolOperatingInd>
      <TrnsfrExmptNonChrtblRltdOrgInd>0</TrnsfrExmptNonChrtblRltdOrgInd>
      <RelatedOrgSect527OrgInd>0</RelatedOrgSect527OrgInd>
      <PartVIOfCompOfHghstPdEmplTxt>NONE</PartVIOfCompOfHghstPdEmplTxt>
      <PartVIHghstPdCntrctProfSrvcTxt>NONE</PartVIHghstPdCntrctProfSrvcTxt>
    </IRS990EZ>
    <IRS990ScheduleA documentId="IRS990ScheduleA">
      <PublicOrganization170Ind>X</PublicOrganization170Ind>
      <GiftsGrantsContriRcvd170Grp>
        <CurrentTaxYearMinus4YearsAmt>272533</CurrentTaxYearMinus4YearsAmt>
        <CurrentTaxYearMinus3YearsAmt>715</CurrentTaxYearMinus3YearsAmt>
        <CurrentTaxYearAmt>43090</CurrentTaxYearAmt>
        <TotalAmt>316338</TotalAmt>
      </GiftsGrantsContriRcvd170Grp>
      <TotalCalendarYear170Grp>
        <CurrentTaxYearMinus4YearsAmt>272533</CurrentTaxYearMinus4YearsAmt>
        <CurrentTaxYearMinus3YearsAmt>715</CurrentTaxYearMinus3YearsAmt>
        <CurrentTaxYearAmt>43090</CurrentTaxYearAmt>
        <TotalAmt>316338</TotalAmt>
      </TotalCalendarYear170Grp>
      <PublicSupportTotal170Amt>316338</PublicSupportTotal170Amt>
      <TotalSupportAmt>316338</TotalSupportAmt>
      <PublicSupportCY170Pct>1</PublicSupportCY170Pct>
      <PublicSupportPY170Pct>0</PublicSupportPY170Pct>
      <DistributableAmountGrp>
        <CYAdjNetIncomeDistributableAmt>0</CYAdjNetIncomeDistributableAmt>
        <CYPct85AdjustedNetIncomeAmt>0</CYPct85AdjustedNetIncomeAmt>
        <CYTotalMinAstDistributableAmt>0</CYTotalMinAstDistributableAmt>
        <CYGreaterAdjustedMinimumAmt>0</CYGreaterAdjustedMinimumAmt>
        <CYIncomeTaxImposedPYAmt>0</CYIncomeTaxImposedPYAmt>
        <CYDistributableAsAdjustedAmt>0</CYDistributableAsAdjustedAmt>
      </DistributableAmountGrp>
    </IRS990ScheduleA>
  </ReturnData>
</Return>
