<?xml version="1.0" encoding="utf-8"?>
<Return returnVersion="2021v4.0" xmlns="http://www.irs.gov/efile" xmlns:xsi="http://www.w3.org/2001/XMLSchema-instance">
  <ReturnHeader binaryAttachmentCnt="0">
    <ReturnTs>2023-03-17T19:25:58-07:00</ReturnTs>
    <TaxPeriodEndDt>2022-05-31</TaxPeriodEndDt>
    <PreparerFirmGrp>
      <PreparerFirmEIN>812956154</PreparerFirmEIN>
      <PreparerFirmName>
        <BusinessNameLine1Txt>Renosi Inc</BusinessNameLine1Txt>
      </PreparerFirmName>
      <PreparerUSAddress>
        <AddressLine1Txt>13506 Summerport Village Parkway</AddressLine1Txt>
        <AddressLine2Txt>1506</AddressLine2Txt>
        <CityNm>Windermere</CityNm>
        <StateAbbreviationCd>FL</StateAbbreviationCd>
        <ZIPCd>34786</ZIPCd>
      </PreparerUSAddress>
    </PreparerFirmGrp>
    <ReturnTypeCd>990EZ</ReturnTypeCd>
    <TaxPeriodBeginDt>2021-06-01</TaxPeriodBeginDt>
    <Filer>
      <EIN>465396079</EIN>
      <BusinessName>
        <BusinessNameLine1Txt>West Forsyth Boys Basketball Booster Club Inc</BusinessNameLine1Txt>
      </BusinessName>
      <BusinessNameControlTxt>WEST</BusinessNameControlTxt>
      <PhoneNum>4042136273</PhoneNum>
      <USAddress>
        <AddressLine1Txt>4155 Drew Road</AddressLine1Txt>
        <CityNm>Cumming</CityNm>
        <StateAbbreviationCd>GA</StateAbbreviationCd>
        <ZIPCd>30040</ZIPCd>
      </USAddress>
    </Filer>
    <BusinessOfficerGrp>
      <PersonNm>Natalie Storm</PersonNm>
      <PersonTitleTxt>Treasurer</PersonTitleTxt>
      <PhoneNum>4076140104</PhoneNum>
      <SignatureDt>2023-03-17</SignatureDt>
      <DiscussWithPaidPreparerInd>1</DiscussWithPaidPreparerInd>
    </BusinessOfficerGrp>
    <PreparerPersonGrp>
      <PreparerPersonNm>Drew Englund</PreparerPersonNm>
      <PTIN>P02156719</PTIN>
      <PhoneNum>4076140112</PhoneNum>
      <PreparationDt>2023-03-17</PreparationDt>
    </PreparerPersonGrp>
    <AdditionalFilerInformation>
      <TrustedCustomerGrp>
        <TrustedCustomerCd>0</TrustedCustomerCd>
        <OOBSecurityVerificationCd>11</OOBSecurityVerificationCd>
        <LastSubmissionRqrOOBCd>1</LastSubmissionRqrOOBCd>
        <AuthenticationAssuranceLevelCd>AAL2</AuthenticationAssuranceLevelCd>
        <ProfilePasswordChangeInd>X</ProfilePasswordChangeInd>
      </TrustedCustomerGrp>
    </AdditionalFilerInformation>
    <TaxYr>2021</TaxYr>
    <BuildTS>2023-04-26 12:10:37Z</BuildTS>
  </ReturnHeader>
  <ReturnData documentCnt="4">
    <IRS990EZ documentId="R000001" referenceDocumentId="R000003 R000004" softwareId="21013178" softwareVersionNum="v1.00">
      <GroupExemptionNum>5271</GroupExemptionNum>
      <MethodOfAccountingCashInd>X</MethodOfAccountingCashInd>
      <ScheduleBNotRequiredInd>X</ScheduleBNotRequiredInd>
      <Organization501c3Ind referenceDocumentId="R000002">X</Organization501c3Ind>
      <TypeOfOrganizationCorpInd>X</TypeOfOrganizationCorpInd>
      <GrossReceiptsAmt>95475</GrossReceiptsAmt>
      <InfoInScheduleOPartIInd>X</InfoInScheduleOPartIInd>
      <ContributionsGiftsGrantsEtcAmt>27701</ContributionsGiftsGrantsEtcAmt>
      <ProgramServiceRevenueAmt>26155</ProgramServiceRevenueAmt>
      <MembershipDuesAmt>38460</MembershipDuesAmt>
      <InvestmentIncomeAmt>0</InvestmentIncomeAmt>
      <SaleOfAssetsGrossAmt>0</SaleOfAssetsGrossAmt>
      <CostOrOtherBasisExpenseSaleAmt>0</CostOrOtherBasisExpenseSaleAmt>
      <GainOrLossFromSaleOfAssetsAmt>0</GainOrLossFromSaleOfAssetsAmt>
      <GamingGrossIncomeAmt>0</GamingGrossIncomeAmt>
      <FundraisingGrossIncomeAmt fndrsngEventContriPrevRptAmt="0">0</FundraisingGrossIncomeAmt>
      <SpecialEventsDirectExpensesAmt>6387</SpecialEventsDirectExpensesAmt>
      <SpecialEventsNetIncomeLossAmt>-6387</SpecialEventsNetIncomeLossAmt>
      <GrossSalesOfInventoryAmt>3149</GrossSalesOfInventoryAmt>
      <CostOfGoodsSoldAmt>3390</CostOfGoodsSoldAmt>
      <GrossProfitLossSlsOfInvntryAmt>-241</GrossProfitLossSlsOfInvntryAmt>
      <OtherRevenueTotalAmt>10</OtherRevenueTotalAmt>
      <TotalRevenueAmt>85698</TotalRevenueAmt>
      <GrantsAndSimilarAmountsPaidAmt>0</GrantsAndSimilarAmountsPaidAmt>
      <BenefitsPaidToOrForMembersAmt>0</BenefitsPaidToOrForMembersAmt>
      <SalariesOtherCompEmplBnftAmt>6300</SalariesOtherCompEmplBnftAmt>
      <FeesAndOtherPymtToIndCntrctAmt>300</FeesAndOtherPymtToIndCntrctAmt>
      <OccupancyRentUtltsAndMaintAmt>0</OccupancyRentUtltsAndMaintAmt>
      <PrintingPublicationsPostageAmt>1643</PrintingPublicationsPostageAmt>
      <OtherExpensesTotalAmt>70627</OtherExpensesTotalAmt>
      <TotalExpensesAmt>78870</TotalExpensesAmt>
      <ExcessOrDeficitForYearAmt>6828</ExcessOrDeficitForYearAmt>
      <NetAssetsOrFundBalancesBOYAmt>5049</NetAssetsOrFundBalancesBOYAmt>
      <OtherChangesInNetAssetsAmt>0</OtherChangesInNetAssetsAmt>
      <NetAssetsOrFundBalancesEOYAmt>11877</NetAssetsOrFundBalancesEOYAmt>
      <CashSavingsAndInvestmentsGrp>
        <BOYAmt>5049</BOYAmt>
        <EOYAmt>11877</EOYAmt>
      </CashSavingsAndInvestmentsGrp>
      <LandAndBuildingsGrp>
        <BOYAmt>0</BOYAmt>
        <EOYAmt>0</EOYAmt>
      </LandAndBuildingsGrp>
      <OtherAssetsTotalDetail>
        <BOYAmt>0</BOYAmt>
        <EOYAmt>0</EOYAmt>
      </OtherAssetsTotalDetail>
      <Form990TotalAssetsGrp>
        <BOYAmt>5049</BOYAmt>
        <EOYAmt>11877</EOYAmt>
      </Form990TotalAssetsGrp>
      <SumOfTotalLiabilitiesGrp>
        <BOYAmt>0</BOYAmt>
        <EOYAmt>0</EOYAmt>
      </SumOfTotalLiabilitiesGrp>
      <NetAssetsOrFundBalancesGrp>
        <BOYAmt>5049</BOYAmt>
        <EOYAmt>11877</EOYAmt>
      </NetAssetsOrFundBalancesGrp>
      <PrimaryExemptPurposeTxt>The purpose of the organization is to support the students, parents, staff, and coaches of the West Forsyth Boys Basketball Programs by recruiting volunteers, raising funds, and conducting events.</PrimaryExemptPurposeTxt>
      <ProgramSrvcAccomplishmentGrp>
        <DescriptionProgramSrvcAccomTxt>Funded Programs: Regionals, training, officials, uniforms, supplies, and other program supplies.</DescriptionProgramSrvcAccomTxt>
        <GrantsAndAllocationsAmt>0</GrantsAndAllocationsAmt>
        <ProgramServiceExpensesAmt>37401</ProgramServiceExpensesAmt>
      </ProgramSrvcAccomplishmentGrp>
      <ProgramSrvcAccomplishmentGrp>
        <DescriptionProgramSrvcAccomTxt>Funded meals and travel costs</DescriptionProgramSrvcAccomTxt>
        <GrantsAndAllocationsAmt>0</GrantsAndAllocationsAmt>
        <ProgramServiceExpensesAmt>14001</ProgramServiceExpensesAmt>
      </ProgramSrvcAccomplishmentGrp>
      <ProgramSrvcAccomplishmentGrp>
        <DescriptionProgramSrvcAccomTxt>Feeder Program</DescriptionProgramSrvcAccomTxt>
        <GrantsAndAllocationsAmt>0</GrantsAndAllocationsAmt>
        <ProgramServiceExpensesAmt>11560</ProgramServiceExpensesAmt>
      </ProgramSrvcAccomplishmentGrp>
      <ProgramSrvcAccomplishmentGrp>
        <DescriptionProgramSrvcAccomTxt>Hosted Events</DescriptionProgramSrvcAccomTxt>
        <GrantsAndAllocationsAmt>0</GrantsAndAllocationsAmt>
        <ProgramServiceExpensesAmt>7545</ProgramServiceExpensesAmt>
      </ProgramSrvcAccomplishmentGrp>
      <TotalProgramServiceExpensesAmt>70507</TotalProgramServiceExpensesAmt>
      <OfficerDirectorTrusteeEmplGrp>
        <PersonNm>Peter Goldberger</PersonNm>
        <TitleTxt>President</TitleTxt>
        <AverageHrsPerWkDevotedToPosRt>0</AverageHrsPerWkDevotedToPosRt>
        <CompensationAmt>0</CompensationAmt>
        <EmployeeBenefitProgramAmt>0</EmployeeBenefitProgramAmt>
        <ExpenseAccountOtherAllwncAmt>0</ExpenseAccountOtherAllwncAmt>
      </OfficerDirectorTrusteeEmplGrp>
      <OfficerDirectorTrusteeEmplGrp>
        <PersonNm>President</PersonNm>
        <TitleTxt>Treasurer</TitleTxt>
        <AverageHrsPerWkDevotedToPosRt>0</AverageHrsPerWkDevotedToPosRt>
        <CompensationAmt>0</CompensationAmt>
        <EmployeeBenefitProgramAmt>0</EmployeeBenefitProgramAmt>
        <ExpenseAccountOtherAllwncAmt>0</ExpenseAccountOtherAllwncAmt>
      </OfficerDirectorTrusteeEmplGrp>
      <OfficerDirectorTrusteeEmplGrp>
        <PersonNm>Chad Damerell</PersonNm>
        <TitleTxt>Secretary</TitleTxt>
        <AverageHrsPerWkDevotedToPosRt>0</AverageHrsPerWkDevotedToPosRt>
        <CompensationAmt>0</CompensationAmt>
        <EmployeeBenefitProgramAmt>0</EmployeeBenefitProgramAmt>
        <ExpenseAccountOtherAllwncAmt>0</ExpenseAccountOtherAllwncAmt>
      </OfficerDirectorTrusteeEmplGrp>
      <ActivitiesNotPreviouslyRptInd>0</ActivitiesNotPreviouslyRptInd>
      <ChgMadeToOrgnzngDocNotRptInd>0</ChgMadeToOrgnzngDocNotRptInd>
      <OrganizationHadUBIInd>0</OrganizationHadUBIInd>
      <SubjectToProxyTaxInd>0</SubjectToProxyTaxInd>
      <OrganizationDissolvedEtcInd>0</OrganizationDissolvedEtcInd>
      <DirectIndirectPltclExpendAmt>0</DirectIndirectPltclExpendAmt>
      <Form1120PolFiledInd>0</Form1120PolFiledInd>
      <MadeLoansToFromOfficersInd>0</MadeLoansToFromOfficersInd>
      <TaxImposedUnderIRC4911Amt>0</TaxImposedUnderIRC4911Amt>
      <TaxImposedUnderIRC4912Amt>0</TaxImposedUnderIRC4912Amt>
      <TaxImposedUnderIRC4955Amt>0</TaxImposedUnderIRC4955Amt>
      <EngagedInExcessBenefitTransInd>0</EngagedInExcessBenefitTransInd>
      <TaxImposedOnOrganizationMgrAmt>0</TaxImposedOnOrganizationMgrAmt>
      <TaxReimbursedByOrganizationAmt>0</TaxReimbursedByOrganizationAmt>
      <ProhibitedTaxShelterTransInd>0</ProhibitedTaxShelterTransInd>
      <BooksInCareOfDetail>
        <PersonNm>Natalie Storm</PersonNm>
        <USAddress>
          <AddressLine1Txt>4155 Drew Road</AddressLine1Txt>
          <CityNm>Cumming</CityNm>
          <StateAbbreviationCd>GA</StateAbbreviationCd>
          <ZIPCd>30040</ZIPCd>
        </USAddress>
        <PhoneNum>4042136273</PhoneNum>
      </BooksInCareOfDetail>
      <ForeignFinancialAccountInd>0</ForeignFinancialAccountInd>
      <ForeignOfficeInd>0</ForeignOfficeInd>
      <DonorAdvisedFndsInd>0</DonorAdvisedFndsInd>
      <OperateHospitalInd>0</OperateHospitalInd>
      <TanningServicesProvidedInd>0</TanningServicesProvidedInd>
      <RelatedOrganizationCtrlEntInd>0</RelatedOrganizationCtrlEntInd>
      <TransactionWithControlEntInd>0</TransactionWithControlEntInd>
      <PoliticalCampaignActyInd>0</PoliticalCampaignActyInd>
      <LobbyingActivitiesInd>0</LobbyingActivitiesInd>
      <SchoolOperatingInd>0</SchoolOperatingInd>
      <TrnsfrExmptNonChrtblRltdOrgInd>0</TrnsfrExmptNonChrtblRltdOrgInd>
      <PartVIOfCompOfHghstPdEmplTxt>NONE</PartVIOfCompOfHghstPdEmplTxt>
      <PartVIHghstPdCntrctProfSrvcTxt>NONE</PartVIHghstPdCntrctProfSrvcTxt>
      <FiledScheduleAInd>1</FiledScheduleAInd>
    </IRS990EZ>
    <IRS990ScheduleA documentId="R000002" softwareId="21013178" softwareVersionNum="v1.00">
      <PubliclySupportedOrg509a2Ind>X</PubliclySupportedOrg509a2Ind>
      <GiftsGrantsContrisRcvd509Grp>
        <CurrentTaxYearMinus4YearsAmt>40383</CurrentTaxYearMinus4YearsAmt>
        <CurrentTaxYearMinus3YearsAmt>40161</CurrentTaxYearMinus3YearsAmt>
        <CurrentTaxYearMinus2YearsAmt>43706</CurrentTaxYearMinus2YearsAmt>
        <CurrentTaxYearMinus1YearAmt>43706</CurrentTaxYearMinus1YearAmt>
        <CurrentTaxYearAmt>66161</CurrentTaxYearAmt>
        <TotalAmt>234117</TotalAmt>
      </GiftsGrantsContrisRcvd509Grp>
      <GrossReceiptsAdmissionsGrp>
        <CurrentTaxYearAmt>29314</CurrentTaxYearAmt>
        <TotalAmt>29314</TotalAmt>
      </GrossReceiptsAdmissionsGrp>
      <Total509Grp>
        <CurrentTaxYearMinus4YearsAmt>40383</CurrentTaxYearMinus4YearsAmt>
        <CurrentTaxYearMinus3YearsAmt>40161</CurrentTaxYearMinus3YearsAmt>
        <CurrentTaxYearMinus2YearsAmt>43706</CurrentTaxYearMinus2YearsAmt>
        <CurrentTaxYearMinus1YearAmt>43706</CurrentTaxYearMinus1YearAmt>
        <CurrentTaxYearAmt>95475</CurrentTaxYearAmt>
        <TotalAmt>263431</TotalAmt>
      </Total509Grp>
      <PublicSupportTotal509Amt>263431</PublicSupportTotal509Amt>
      <TotalSupportCalendarYearGrp>
        <CurrentTaxYearMinus4YearsAmt>40383</CurrentTaxYearMinus4YearsAmt>
        <CurrentTaxYearMinus3YearsAmt>40161</CurrentTaxYearMinus3YearsAmt>
        <CurrentTaxYearMinus2YearsAmt>43706</CurrentTaxYearMinus2YearsAmt>
        <CurrentTaxYearMinus1YearAmt>43706</CurrentTaxYearMinus1YearAmt>
        <CurrentTaxYearAmt>95475</CurrentTaxYearAmt>
        <TotalAmt>263431</TotalAmt>
      </TotalSupportCalendarYearGrp>
      <PublicSupportCY509Pct>1</PublicSupportCY509Pct>
      <PublicSupportPY509Pct>1</PublicSupportPY509Pct>
      <InvestmentIncomeCYPct>0</InvestmentIncomeCYPct>
      <InvestmentIncomePYPct>0</InvestmentIncomePYPct>
      <ThirtyThrPctSuprtTestsCY509Ind>X</ThirtyThrPctSuprtTestsCY509Ind>
    </IRS990ScheduleA>
    <IRS990ScheduleO documentId="R000003" softwareId="21013178" softwareVersionNum="v1.00">
      <SupplementalInformationDetail>
        <FormAndLineReferenceDesc>Form 990-EZ, Part I, Line 8</FormAndLineReferenceDesc>
        <ExplanationTxt>Refund</ExplanationTxt>
      </SupplementalInformationDetail>
      <SupplementalInformationDetail>
        <FormAndLineReferenceDesc>Form 990-EZ, Part I, Line 16</FormAndLineReferenceDesc>
        <ExplanationTxt>Description;Amount^Funded Programs;37401|Meals and Travel;14001|Feeder Programs;11560|Events;7545|Banking;120^Total;70627^</ExplanationTxt>
      </SupplementalInformationDetail>
    </IRS990ScheduleO>
    <ReasonableCauseExplanation documentId="R000004" softwareId="21013178" softwareVersionNum="v1.00">
      <ExplanationTxt>An extension was filed.</ExplanationTxt>
    </ReasonableCauseExplanation>
  </ReturnData>
</Return>