<?xml version="1.0" encoding="utf-8"?>
<Return returnVersion="2022v4.0" xmlns="http://www.irs.gov/efile" xmlns:xsi="http://www.w3.org/2001/XMLSchema-instance">
  <ReturnHeader binaryAttachmentCnt="0">
    <ReturnTs>2023-03-12T11:09:52-07:00</ReturnTs>
    <TaxPeriodEndDt>2022-12-31</TaxPeriodEndDt>
    <ReturnTypeCd>990EZ</ReturnTypeCd>
    <TaxPeriodBeginDt>2022-01-01</TaxPeriodBeginDt>
    <Filer>
      <EIN>541704367</EIN>
      <BusinessName>
        <BusinessNameLine1Txt>GREAT CHESAPEAKE SCHOONER RACE INC</BusinessNameLine1Txt>
      </BusinessName>
      <BusinessNameControlTxt>GREA</BusinessNameControlTxt>
      <PhoneNum>8047257999</PhoneNum>
      <USAddress>
        <AddressLine1Txt>PO Box 127</AddressLine1Txt>
        <CityNm>Mobjack</CityNm>
        <StateAbbreviationCd>VA</StateAbbreviationCd>
        <ZIPCd>23056</ZIPCd>
      </USAddress>
    </Filer>
    <BusinessOfficerGrp>
      <PersonNm>Keith Jones</PersonNm>
      <PersonTitleTxt>Treasurer</PersonTitleTxt>
      <PhoneNum>8047257999</PhoneNum>
      <SignatureDt>2023-03-12</SignatureDt>
    </BusinessOfficerGrp>
    <IRSResponsiblePrtyInfoCurrInd>1</IRSResponsiblePrtyInfoCurrInd>
    <AdditionalFilerInformation>
      <TrustedCustomerGrp>
        <TrustedCustomerCd>0</TrustedCustomerCd>
        <OOBSecurityVerificationCd>11</OOBSecurityVerificationCd>
        <LastSubmissionRqrOOBCd>0</LastSubmissionRqrOOBCd>
        <AuthenticationAssuranceLevelCd>AAL2</AuthenticationAssuranceLevelCd>
      </TrustedCustomerGrp>
    </AdditionalFilerInformation>
    <TaxYr>2022</TaxYr>
    <BuildTS>2023-04-26 12:10:37Z</BuildTS>
  </ReturnHeader>
  <ReturnData documentCnt="3">
    <IRS990EZ documentId="R000001" referenceDocumentId="R000003" softwareId="22015720" softwareVersionNum="v1.00">
      <MethodOfAccountingCashInd>X</MethodOfAccountingCashInd>
      <ScheduleBNotRequiredInd>X</ScheduleBNotRequiredInd>
      <WebsiteAddressTxt>www.gcbsr.org</WebsiteAddressTxt>
      <Organization501c3Ind referenceDocumentId="R000002">X</Organization501c3Ind>
      <TypeOfOrganizationCorpInd>X</TypeOfOrganizationCorpInd>
      <GrossReceiptsAmt>67983</GrossReceiptsAmt>
      <InfoInScheduleOPartIInd>X</InfoInScheduleOPartIInd>
      <ContributionsGiftsGrantsEtcAmt>34772</ContributionsGiftsGrantsEtcAmt>
      <ProgramServiceRevenueAmt>27162</ProgramServiceRevenueAmt>
      <MembershipDuesAmt>0</MembershipDuesAmt>
      <InvestmentIncomeAmt>0</InvestmentIncomeAmt>
      <SaleOfAssetsGrossAmt>0</SaleOfAssetsGrossAmt>
      <CostOrOtherBasisExpenseSaleAmt>0</CostOrOtherBasisExpenseSaleAmt>
      <GainOrLossFromSaleOfAssetsAmt>0</GainOrLossFromSaleOfAssetsAmt>
      <GamingGrossIncomeAmt>0</GamingGrossIncomeAmt>
      <FundraisingGrossIncomeAmt fndrsngEventContriPrevRptAmt="0">0</FundraisingGrossIncomeAmt>
      <SpecialEventsDirectExpensesAmt>0</SpecialEventsDirectExpensesAmt>
      <SpecialEventsNetIncomeLossAmt>0</SpecialEventsNetIncomeLossAmt>
      <GrossSalesOfInventoryAmt>6049</GrossSalesOfInventoryAmt>
      <CostOfGoodsSoldAmt>5033</CostOfGoodsSoldAmt>
      <GrossProfitLossSlsOfInvntryAmt>1016</GrossProfitLossSlsOfInvntryAmt>
      <OtherRevenueTotalAmt>0</OtherRevenueTotalAmt>
      <TotalRevenueAmt>62950</TotalRevenueAmt>
      <GrantsAndSimilarAmountsPaidAmt>39369</GrantsAndSimilarAmountsPaidAmt>
      <BenefitsPaidToOrForMembersAmt>0</BenefitsPaidToOrForMembersAmt>
      <SalariesOtherCompEmplBnftAmt>0</SalariesOtherCompEmplBnftAmt>
      <FeesAndOtherPymtToIndCntrctAmt>0</FeesAndOtherPymtToIndCntrctAmt>
      <OccupancyRentUtltsAndMaintAmt>0</OccupancyRentUtltsAndMaintAmt>
      <PrintingPublicationsPostageAmt>0</PrintingPublicationsPostageAmt>
      <OtherExpensesTotalAmt>6551</OtherExpensesTotalAmt>
      <TotalExpensesAmt>45920</TotalExpensesAmt>
      <ExcessOrDeficitForYearAmt>17030</ExcessOrDeficitForYearAmt>
      <NetAssetsOrFundBalancesBOYAmt>75264</NetAssetsOrFundBalancesBOYAmt>
      <OtherChangesInNetAssetsAmt>0</OtherChangesInNetAssetsAmt>
      <NetAssetsOrFundBalancesEOYAmt>92294</NetAssetsOrFundBalancesEOYAmt>
      <CashSavingsAndInvestmentsGrp>
        <BOYAmt>75264</BOYAmt>
        <EOYAmt>92294</EOYAmt>
      </CashSavingsAndInvestmentsGrp>
      <LandAndBuildingsGrp>
        <BOYAmt>0</BOYAmt>
        <EOYAmt>0</EOYAmt>
      </LandAndBuildingsGrp>
      <OtherAssetsTotalDetail>
        <BOYAmt>0</BOYAmt>
        <EOYAmt>0</EOYAmt>
      </OtherAssetsTotalDetail>
      <Form990TotalAssetsGrp>
        <BOYAmt>75264</BOYAmt>
        <EOYAmt>92294</EOYAmt>
      </Form990TotalAssetsGrp>
      <SumOfTotalLiabilitiesGrp>
        <BOYAmt>0</BOYAmt>
        <EOYAmt>0</EOYAmt>
      </SumOfTotalLiabilitiesGrp>
      <NetAssetsOrFundBalancesGrp>
        <BOYAmt>75264</BOYAmt>
        <EOYAmt>92294</EOYAmt>
      </NetAssetsOrFundBalancesGrp>
      <PrimaryExemptPurposeTxt>To promote awareness of the Chesapeake Bay's heritage * Encourage preservation of the Bay's resources * Support Chesapeake Bay education and clean-up efforts * Bring historic schooners to the Bay * Encourage schooner sailing and preservation</PrimaryExemptPurposeTxt>
      <ProgramSrvcAccomplishmentGrp>
        <DescriptionProgramSrvcAccomTxt>Annapolis Parks &amp; Recreation, Annapolis, MD - Youth Education Sail on Schooner Woodwind - $2,064.67 - 40 Students</DescriptionProgramSrvcAccomTxt>
        <GrantsAndAllocationsAmt>2065</GrantsAndAllocationsAmt>
        <ProgramServiceExpensesAmt>0</ProgramServiceExpensesAmt>
      </ProgramSrvcAccomplishmentGrp>
      <ProgramSrvcAccomplishmentGrp>
        <DescriptionProgramSrvcAccomTxt>Pride of Baltimore Inc. - Education Sail on Pride of Baltimore II - $1,000.00 - 32 Students</DescriptionProgramSrvcAccomTxt>
        <GrantsAndAllocationsAmt>1000</GrantsAndAllocationsAmt>
        <ProgramServiceExpensesAmt>0</ProgramServiceExpensesAmt>
      </ProgramSrvcAccomplishmentGrp>
      <ProgramSrvcAccomplishmentGrp>
        <DescriptionProgramSrvcAccomTxt>Living Classrooms Foundation - Education Sail on Mildred Belle and Sigsbee - $2,000.00 - 56 Students</DescriptionProgramSrvcAccomTxt>
        <GrantsAndAllocationsAmt>2000</GrantsAndAllocationsAmt>
        <ProgramServiceExpensesAmt>0</ProgramServiceExpensesAmt>
      </ProgramSrvcAccomplishmentGrp>
      <ProgramSrvcAccomplishmentGrp>
        <DescriptionProgramSrvcAccomTxt>The Great Chesapeake Bay Schooner Race was founded in 1990. This annual event starts in Baltimore with dockside public viewing, education (STEM-H) programs aboard and underway for local school children, and a Parade of Sail to Baltimore's Inner Harbor. The race starts at the Bay Bridge and finishes at Thimble Shoals, participants dock in Norfolk for public viewing and an awards ceremony. Education programs for local school children are given (depending on holiday and Covid). Participation in the events is approximately 500 people. The cost of the GCBSR event in 2022 was $34,304.</DescriptionProgramSrvcAccomTxt>
        <GrantsAndAllocationsAmt>0</GrantsAndAllocationsAmt>
        <ProgramServiceExpensesAmt>34304</ProgramServiceExpensesAmt>
      </ProgramSrvcAccomplishmentGrp>
      <TotalProgramServiceExpensesAmt>34304</TotalProgramServiceExpensesAmt>
      <OfficerDirectorTrusteeEmplGrp>
        <PersonNm>Steven Briggs</PersonNm>
        <TitleTxt>President</TitleTxt>
        <AverageHrsPerWkDevotedToPosRt>3.5</AverageHrsPerWkDevotedToPosRt>
        <CompensationAmt>0</CompensationAmt>
        <EmployeeBenefitProgramAmt>0</EmployeeBenefitProgramAmt>
        <ExpenseAccountOtherAllwncAmt>0</ExpenseAccountOtherAllwncAmt>
      </OfficerDirectorTrusteeEmplGrp>
      <OfficerDirectorTrusteeEmplGrp>
        <PersonNm>Duncan Hood</PersonNm>
        <TitleTxt>Chairperson</TitleTxt>
        <AverageHrsPerWkDevotedToPosRt>3</AverageHrsPerWkDevotedToPosRt>
        <CompensationAmt>0</CompensationAmt>
        <EmployeeBenefitProgramAmt>0</EmployeeBenefitProgramAmt>
        <ExpenseAccountOtherAllwncAmt>0</ExpenseAccountOtherAllwncAmt>
      </OfficerDirectorTrusteeEmplGrp>
      <OfficerDirectorTrusteeEmplGrp>
        <PersonNm>Paul Carroll</PersonNm>
        <TitleTxt>Vice President</TitleTxt>
        <AverageHrsPerWkDevotedToPosRt>3</AverageHrsPerWkDevotedToPosRt>
        <CompensationAmt>0</CompensationAmt>
        <EmployeeBenefitProgramAmt>0</EmployeeBenefitProgramAmt>
        <ExpenseAccountOtherAllwncAmt>0</ExpenseAccountOtherAllwncAmt>
      </OfficerDirectorTrusteeEmplGrp>
      <OfficerDirectorTrusteeEmplGrp>
        <PersonNm>Jennifer Kaye</PersonNm>
        <TitleTxt>Secretary</TitleTxt>
        <AverageHrsPerWkDevotedToPosRt>1.5</AverageHrsPerWkDevotedToPosRt>
        <CompensationAmt>0</CompensationAmt>
        <EmployeeBenefitProgramAmt>0</EmployeeBenefitProgramAmt>
        <ExpenseAccountOtherAllwncAmt>0</ExpenseAccountOtherAllwncAmt>
      </OfficerDirectorTrusteeEmplGrp>
      <OfficerDirectorTrusteeEmplGrp>
        <PersonNm>Keith Jones</PersonNm>
        <TitleTxt>Treasurer</TitleTxt>
        <AverageHrsPerWkDevotedToPosRt>4</AverageHrsPerWkDevotedToPosRt>
        <CompensationAmt>0</CompensationAmt>
        <EmployeeBenefitProgramAmt>0</EmployeeBenefitProgramAmt>
        <ExpenseAccountOtherAllwncAmt>0</ExpenseAccountOtherAllwncAmt>
      </OfficerDirectorTrusteeEmplGrp>
      <OfficerDirectorTrusteeEmplGrp>
        <PersonNm>Caryn West</PersonNm>
        <TitleTxt>Director</TitleTxt>
        <AverageHrsPerWkDevotedToPosRt>2</AverageHrsPerWkDevotedToPosRt>
        <CompensationAmt>0</CompensationAmt>
        <EmployeeBenefitProgramAmt>0</EmployeeBenefitProgramAmt>
        <ExpenseAccountOtherAllwncAmt>0</ExpenseAccountOtherAllwncAmt>
      </OfficerDirectorTrusteeEmplGrp>
      <OfficerDirectorTrusteeEmplGrp>
        <PersonNm>Nan Nawrocki</PersonNm>
        <TitleTxt>Director</TitleTxt>
        <AverageHrsPerWkDevotedToPosRt>2.5</AverageHrsPerWkDevotedToPosRt>
        <CompensationAmt>0</CompensationAmt>
        <EmployeeBenefitProgramAmt>0</EmployeeBenefitProgramAmt>
        <ExpenseAccountOtherAllwncAmt>0</ExpenseAccountOtherAllwncAmt>
      </OfficerDirectorTrusteeEmplGrp>
      <OfficerDirectorTrusteeEmplGrp>
        <PersonNm>Stacy Spaulding</PersonNm>
        <TitleTxt>Director</TitleTxt>
        <AverageHrsPerWkDevotedToPosRt>3</AverageHrsPerWkDevotedToPosRt>
        <CompensationAmt>0</CompensationAmt>
        <EmployeeBenefitProgramAmt>0</EmployeeBenefitProgramAmt>
        <ExpenseAccountOtherAllwncAmt>0</ExpenseAccountOtherAllwncAmt>
      </OfficerDirectorTrusteeEmplGrp>
      <OfficerDirectorTrusteeEmplGrp>
        <PersonNm>Jamie Van Pelt</PersonNm>
        <TitleTxt>Director</TitleTxt>
        <AverageHrsPerWkDevotedToPosRt>2</AverageHrsPerWkDevotedToPosRt>
        <CompensationAmt>0</CompensationAmt>
        <EmployeeBenefitProgramAmt>0</EmployeeBenefitProgramAmt>
        <ExpenseAccountOtherAllwncAmt>0</ExpenseAccountOtherAllwncAmt>
      </OfficerDirectorTrusteeEmplGrp>
      <ActivitiesNotPreviouslyRptInd>0</ActivitiesNotPreviouslyRptInd>
      <ChgMadeToOrgnzngDocNotRptInd>0</ChgMadeToOrgnzngDocNotRptInd>
      <OrganizationHadUBIInd>0</OrganizationHadUBIInd>
      <SubjectToProxyTaxInd>0</SubjectToProxyTaxInd>
      <OrganizationDissolvedEtcInd>0</OrganizationDissolvedEtcInd>
      <DirectIndirectPltclExpendAmt>0</DirectIndirectPltclExpendAmt>
      <Form1120PolFiledInd>0</Form1120PolFiledInd>
      <MadeLoansToFromOfficersInd>0</MadeLoansToFromOfficersInd>
      <TaxImposedUnderIRC4911Amt>0</TaxImposedUnderIRC4911Amt>
      <TaxImposedUnderIRC4912Amt>0</TaxImposedUnderIRC4912Amt>
      <TaxImposedUnderIRC4955Amt>0</TaxImposedUnderIRC4955Amt>
      <EngagedInExcessBenefitTransInd>0</EngagedInExcessBenefitTransInd>
      <TaxImposedOnOrganizationMgrAmt>0</TaxImposedOnOrganizationMgrAmt>
      <TaxReimbursedByOrganizationAmt>0</TaxReimbursedByOrganizationAmt>
      <ProhibitedTaxShelterTransInd>0</ProhibitedTaxShelterTransInd>
      <StatesWhereCopyOfReturnIsFldCd>VA</StatesWhereCopyOfReturnIsFldCd>
      <BooksInCareOfDetail>
        <PersonNm>Keith Jones</PersonNm>
        <USAddress>
          <AddressLine1Txt>PO Box 127</AddressLine1Txt>
          <CityNm>Mobjack</CityNm>
          <StateAbbreviationCd>VA</StateAbbreviationCd>
          <ZIPCd>230560127</ZIPCd>
        </USAddress>
        <PhoneNum>8047257999</PhoneNum>
      </BooksInCareOfDetail>
      <ForeignFinancialAccountInd>0</ForeignFinancialAccountInd>
      <ForeignOfficeInd>0</ForeignOfficeInd>
      <DonorAdvisedFndsInd>0</DonorAdvisedFndsInd>
      <OperateHospitalInd>0</OperateHospitalInd>
      <TanningServicesProvidedInd>0</TanningServicesProvidedInd>
      <RelatedOrganizationCtrlEntInd>0</RelatedOrganizationCtrlEntInd>
      <TransactionWithControlEntInd>0</TransactionWithControlEntInd>
      <PoliticalCampaignActyInd>0</PoliticalCampaignActyInd>
      <LobbyingActivitiesInd>0</LobbyingActivitiesInd>
      <SchoolOperatingInd>0</SchoolOperatingInd>
      <TrnsfrExmptNonChrtblRltdOrgInd>0</TrnsfrExmptNonChrtblRltdOrgInd>
      <PartVIOfCompOfHghstPdEmplTxt>NONE</PartVIOfCompOfHghstPdEmplTxt>
      <PartVIHghstPdCntrctProfSrvcTxt>NONE</PartVIHghstPdCntrctProfSrvcTxt>
      <FiledScheduleAInd>1</FiledScheduleAInd>
    </IRS990EZ>
    <IRS990ScheduleA documentId="R000002" softwareId="22015720" softwareVersionNum="v1.00">
      <PubliclySupportedOrg509a2Ind>X</PubliclySupportedOrg509a2Ind>
      <GiftsGrantsContrisRcvd509Grp>
        <CurrentTaxYearMinus4YearsAmt>19381</CurrentTaxYearMinus4YearsAmt>
        <CurrentTaxYearMinus3YearsAmt>19779</CurrentTaxYearMinus3YearsAmt>
        <CurrentTaxYearMinus2YearsAmt>9932</CurrentTaxYearMinus2YearsAmt>
        <CurrentTaxYearMinus1YearAmt>57135</CurrentTaxYearMinus1YearAmt>
        <CurrentTaxYearAmt>34772</CurrentTaxYearAmt>
        <TotalAmt>140999</TotalAmt>
      </GiftsGrantsContrisRcvd509Grp>
      <GrossReceiptsAdmissionsGrp>
        <CurrentTaxYearMinus4YearsAmt>30614</CurrentTaxYearMinus4YearsAmt>
        <CurrentTaxYearMinus3YearsAmt>30363</CurrentTaxYearMinus3YearsAmt>
        <CurrentTaxYearMinus2YearsAmt>660</CurrentTaxYearMinus2YearsAmt>
        <CurrentTaxYearMinus1YearAmt>30680</CurrentTaxYearMinus1YearAmt>
        <CurrentTaxYearAmt>33211</CurrentTaxYearAmt>
        <TotalAmt>125528</TotalAmt>
      </GrossReceiptsAdmissionsGrp>
      <Total509Grp>
        <CurrentTaxYearMinus4YearsAmt>49995</CurrentTaxYearMinus4YearsAmt>
        <CurrentTaxYearMinus3YearsAmt>50142</CurrentTaxYearMinus3YearsAmt>
        <CurrentTaxYearMinus2YearsAmt>10592</CurrentTaxYearMinus2YearsAmt>
        <CurrentTaxYearMinus1YearAmt>87815</CurrentTaxYearMinus1YearAmt>
        <CurrentTaxYearAmt>67983</CurrentTaxYearAmt>
        <TotalAmt>266527</TotalAmt>
      </Total509Grp>
      <PublicSupportTotal509Amt>266527</PublicSupportTotal509Amt>
      <TotalSupportCalendarYearGrp>
        <CurrentTaxYearMinus4YearsAmt>49995</CurrentTaxYearMinus4YearsAmt>
        <CurrentTaxYearMinus3YearsAmt>50142</CurrentTaxYearMinus3YearsAmt>
        <CurrentTaxYearMinus2YearsAmt>10592</CurrentTaxYearMinus2YearsAmt>
        <CurrentTaxYearMinus1YearAmt>87815</CurrentTaxYearMinus1YearAmt>
        <CurrentTaxYearAmt>67983</CurrentTaxYearAmt>
        <TotalAmt>266527</TotalAmt>
      </TotalSupportCalendarYearGrp>
      <PublicSupportCY509Pct>1</PublicSupportCY509Pct>
      <PublicSupportPY509Pct>1</PublicSupportPY509Pct>
      <InvestmentIncomeCYPct>0</InvestmentIncomeCYPct>
      <InvestmentIncomePYPct>0</InvestmentIncomePYPct>
      <ThirtyThrPctSuprtTestsCY509Ind>X</ThirtyThrPctSuprtTestsCY509Ind>
    </IRS990ScheduleA>
    <IRS990ScheduleO documentId="R000003" softwareId="22015720" softwareVersionNum="v1.00">
      <SupplementalInformationDetail>
        <FormAndLineReferenceDesc>Form 990-EZ, Part I, Line 16</FormAndLineReferenceDesc>
        <ExplanationTxt>Description;Amount^Advertising;618|Credit Card Fees and bank charges;1908|Legal Filing Fees;25|Software License Fees;1470|Web Domain;434|Cost of merchandise for donors;1880|Postage;216^Total;6551^</ExplanationTxt>
      </SupplementalInformationDetail>
    </IRS990ScheduleO>
  </ReturnData>
</Return>