<?xml version="1.0" encoding="utf-8"?>
<Return xmlns="http://www.irs.gov/efile" xmlns:xsi="http://www.w3.org/2001/XMLSchema-instance" returnVersion="2020v4.0" xsi:schemaLocation="http://www.irs.gov/efile">
  <ReturnHeader binaryAttachmentCnt="0">
    <ReturnTs>2023-03-07T12:58:42-08:00</ReturnTs>
    <TaxPeriodEndDt>2021-08-31</TaxPeriodEndDt>
    <PreparerFirmGrp>
      <PreparerFirmEIN>464370753</PreparerFirmEIN>
      <PreparerFirmName>
        <BusinessNameLine1Txt>Baldwin Moffitt Behm LLP</BusinessNameLine1Txt>
      </PreparerFirmName>
      <PreparerUSAddress>
        <AddressLine1Txt>8399 E Indian School Rd Suite 201</AddressLine1Txt>
        <CityNm>Scottsdale</CityNm>
        <StateAbbreviationCd>AZ</StateAbbreviationCd>
        <ZIPCd>85251</ZIPCd>
      </PreparerUSAddress>
    </PreparerFirmGrp>
    <ReturnTypeCd>990</ReturnTypeCd>
    <TaxPeriodBeginDt>2020-09-01</TaxPeriodBeginDt>
    <Filer>
      <EIN>956259492</EIN>
      <BusinessName>
        <BusinessNameLine1Txt>Union Roofers Vacation Fund</BusinessNameLine1Txt>
      </BusinessName>
      <BusinessNameControlTxt>UNIO</BusinessNameControlTxt>
      <PhoneNum>5629271434</PhoneNum>
      <USAddress>
        <AddressLine1Txt>9901 Paramount Blvd 211</AddressLine1Txt>
        <CityNm>Downey</CityNm>
        <StateAbbreviationCd>CA</StateAbbreviationCd>
        <ZIPCd>90240</ZIPCd>
      </USAddress>
    </Filer>
    <BusinessOfficerGrp>
      <PersonNm>BRENT BEASLEY</PersonNm>
      <PersonTitleTxt>Chairman</PersonTitleTxt>
      <SignatureDt>2023-03-07</SignatureDt>
      <DiscussWithPaidPreparerInd>true</DiscussWithPaidPreparerInd>
    </BusinessOfficerGrp>
    <SigningOfficerGrp>
      <PersonFullName>
        <PersonFirstNm>BRENT</PersonFirstNm>
        <PersonLastNm>BEASLEY</PersonLastNm>
      </PersonFullName>
      <SSN>999009999</SSN>
    </SigningOfficerGrp>
    <PreparerPersonGrp>
      <PreparerPersonNm>Robert H Baldwin</PreparerPersonNm>
      <PTIN>P00815972</PTIN>
      <PhoneNum>4807369200</PhoneNum>
    </PreparerPersonGrp>
    <AdditionalFilerInformation>
      <TrustedCustomerGrp>
        <TrustedCustomerCd>0</TrustedCustomerCd>
        <AuthenticationAssuranceLevelCd>AAL1</AuthenticationAssuranceLevelCd>
        <IdentityAssuranceLevelCd>IAL1</IdentityAssuranceLevelCd>
        <FederatedAssuranceLevelCd>FAL1</FederatedAssuranceLevelCd>
      </TrustedCustomerGrp>
    </AdditionalFilerInformation>
    <TaxYr>2020</TaxYr>
    <BuildTS>2023-04-26 12:10:37Z</BuildTS>
  </ReturnHeader>
  <ReturnData documentCnt="4">
    <IRS990 documentId="IRS990" referenceDocumentId="IRS990ScheduleO" softwareId="20011551" softwareVersionNum="2020v4.0">
      <PrincipalOfficerNm>BRENT BEASLEY</PrincipalOfficerNm>
      <USAddress>
        <AddressLine1Txt>9901 Paramount Blvd 211</AddressLine1Txt>
        <CityNm>Downey</CityNm>
        <StateAbbreviationCd>CA</StateAbbreviationCd>
        <ZIPCd>90240</ZIPCd>
      </USAddress>
      <GrossReceiptsAmt>6039414</GrossReceiptsAmt>
      <GroupReturnForAffiliatesInd>false</GroupReturnForAffiliatesInd>
      <Organization501cInd organization501cTypeTxt="9">X</Organization501cInd>
      <WebsiteAddressTxt>N/A</WebsiteAddressTxt>
      <TypeOfOrganizationTrustInd>X</TypeOfOrganizationTrustInd>
      <FormationYr>1967</FormationYr>
      <LegalDomicileStateCd>CA</LegalDomicileStateCd>
      <ActivityOrMissionDesc>DISTRIBUTION OF VACATION CHECKS</ActivityOrMissionDesc>
      <VotingMembersGoverningBodyCnt>4</VotingMembersGoverningBodyCnt>
      <VotingMembersIndependentCnt>4</VotingMembersIndependentCnt>
      <TotalEmployeeCnt>0</TotalEmployeeCnt>
      <TotalVolunteersCnt>4</TotalVolunteersCnt>
      <TotalGrossUBIAmt>0</TotalGrossUBIAmt>
      <CYContributionsGrantsAmt>0</CYContributionsGrantsAmt>
      <PYProgramServiceRevenueAmt>53132</PYProgramServiceRevenueAmt>
      <CYProgramServiceRevenueAmt>6037360</CYProgramServiceRevenueAmt>
      <PYInvestmentIncomeAmt>20027</PYInvestmentIncomeAmt>
      <CYInvestmentIncomeAmt>883</CYInvestmentIncomeAmt>
      <CYOtherRevenueAmt>1171</CYOtherRevenueAmt>
      <PYTotalRevenueAmt>73159</PYTotalRevenueAmt>
      <CYTotalRevenueAmt>6039414</CYTotalRevenueAmt>
      <CYGrantsAndSimilarPaidAmt>0</CYGrantsAndSimilarPaidAmt>
      <CYBenefitsPaidToMembersAmt>6008245</CYBenefitsPaidToMembersAmt>
      <CYSalariesCompEmpBnftPaidAmt>0</CYSalariesCompEmpBnftPaidAmt>
      <CYTotalProfFndrsngExpnsAmt>0</CYTotalProfFndrsngExpnsAmt>
      <CYTotalFundraisingExpenseAmt>0</CYTotalFundraisingExpenseAmt>
      <PYOtherExpensesAmt>60419</PYOtherExpensesAmt>
      <CYOtherExpensesAmt>58481</CYOtherExpensesAmt>
      <PYTotalExpensesAmt>60419</PYTotalExpensesAmt>
      <CYTotalExpensesAmt>6066726</CYTotalExpensesAmt>
      <PYRevenuesLessExpensesAmt>12740</PYRevenuesLessExpensesAmt>
      <CYRevenuesLessExpensesAmt>-27312</CYRevenuesLessExpensesAmt>
      <TotalAssetsBOYAmt>2879682</TotalAssetsBOYAmt>
      <TotalAssetsEOYAmt>2516032</TotalAssetsEOYAmt>
      <TotalLiabilitiesBOYAmt>2566236</TotalLiabilitiesBOYAmt>
      <TotalLiabilitiesEOYAmt>2234735</TotalLiabilitiesEOYAmt>
      <NetAssetsOrFundBalancesBOYAmt>313446</NetAssetsOrFundBalancesBOYAmt>
      <NetAssetsOrFundBalancesEOYAmt>281297</NetAssetsOrFundBalancesEOYAmt>
      <MissionDesc>COLLECTION AND DISTRIBUTION OF VACATION CHECKS</MissionDesc>
      <SignificantNewProgramSrvcInd>false</SignificantNewProgramSrvcInd>
      <SignificantChangeInd>false</SignificantChangeInd>
      <Desc>SERVICES PERFORMED IN CONNECTION WITH CONTRIBUTIONS FROM EMPLOYERS AND ISSUANCE OF VACATION BENEFIT CHECKS FOR APPROXIMATELY 2,100 PLAN PARTICIPANTS.</Desc>
      <DescribedInSection501c3Ind>false</DescribedInSection501c3Ind>
      <ScheduleBRequiredInd>false</ScheduleBRequiredInd>
      <PoliticalCampaignActyInd>false</PoliticalCampaignActyInd>
      <SubjectToProxyTaxInd>false</SubjectToProxyTaxInd>
      <DonorAdvisedFundInd referenceDocumentId="IRS990ScheduleD">false</DonorAdvisedFundInd>
      <ConservationEasementsInd referenceDocumentId="IRS990ScheduleD">false</ConservationEasementsInd>
      <CollectionsOfArtInd referenceDocumentId="IRS990ScheduleD">false</CollectionsOfArtInd>
      <CreditCounselingInd referenceDocumentId="IRS990ScheduleD">false</CreditCounselingInd>
      <DonorRstrOrQuasiEndowmentsInd referenceDocumentId="IRSScheduleD">false</DonorRstrOrQuasiEndowmentsInd>
      <ReportLandBuildingEquipmentInd referenceDocumentId="IRS990ScheduleD">false</ReportLandBuildingEquipmentInd>
      <ReportInvestmentsOtherSecInd referenceDocumentId="IRS990ScheduleD">false</ReportInvestmentsOtherSecInd>
      <ReportProgramRelatedInvstInd referenceDocumentId="IRS990ScheduleD">false</ReportProgramRelatedInvstInd>
      <ReportOtherAssetsInd referenceDocumentId="IRS990ScheduleD">false</ReportOtherAssetsInd>
      <ReportOtherLiabilitiesInd referenceDocumentId="IRS990ScheduleD">true</ReportOtherLiabilitiesInd>
      <IncludeFIN48FootnoteInd referenceDocumentId="IRS990ScheduleD">true</IncludeFIN48FootnoteInd>
      <IndependentAuditFinclStmtInd referenceDocumentId="IRS990ScheduleD">true</IndependentAuditFinclStmtInd>
      <ConsolidatedAuditFinclStmtInd referenceDocumentId="IRS990ScheduleD">false</ConsolidatedAuditFinclStmtInd>
      <SchoolOperatingInd>false</SchoolOperatingInd>
      <ForeignOfficeInd>false</ForeignOfficeInd>
      <ForeignActivitiesInd>false</ForeignActivitiesInd>
      <MoreThan5000KToOrgInd>false</MoreThan5000KToOrgInd>
      <MoreThan5000KToIndividualsInd>false</MoreThan5000KToIndividualsInd>
      <ProfessionalFundraisingInd>false</ProfessionalFundraisingInd>
      <FundraisingActivitiesInd>false</FundraisingActivitiesInd>
      <GamingActivitiesInd>false</GamingActivitiesInd>
      <OperateHospitalInd>false</OperateHospitalInd>
      <GrantsToOrganizationsInd>false</GrantsToOrganizationsInd>
      <GrantsToIndividualsInd>false</GrantsToIndividualsInd>
      <ScheduleJRequiredInd>false</ScheduleJRequiredInd>
      <TaxExemptBondsInd>false</TaxExemptBondsInd>
      <LoanOutstandingInd>false</LoanOutstandingInd>
      <GrantToRelatedPersonInd>false</GrantToRelatedPersonInd>
      <BusinessRlnWithOrgMemInd>false</BusinessRlnWithOrgMemInd>
      <BusinessRlnWithFamMemInd>false</BusinessRlnWithFamMemInd>
      <BusinessRlnWith35CtrlEntInd>false</BusinessRlnWith35CtrlEntInd>
      <DeductibleNonCashContriInd>false</DeductibleNonCashContriInd>
      <DeductibleArtContributionInd>false</DeductibleArtContributionInd>
      <TerminateOperationsInd>false</TerminateOperationsInd>
      <PartialLiquidationInd>false</PartialLiquidationInd>
      <DisregardedEntityInd referenceDocumentId="IRS990ScheduleR">false</DisregardedEntityInd>
      <RelatedEntityInd referenceDocumentId="IRS990ScheduleR">true</RelatedEntityInd>
      <RelatedOrganizationCtrlEntInd>false</RelatedOrganizationCtrlEntInd>
      <ActivitiesConductedPrtshpInd referenceDocumentId="IRS990ScheduleR">false</ActivitiesConductedPrtshpInd>
      <ScheduleORequiredInd>true</ScheduleORequiredInd>
      <IRPDocumentCnt>0</IRPDocumentCnt>
      <IRPDocumentW2GCnt>0</IRPDocumentW2GCnt>
      <BackupWthldComplianceInd>false</BackupWthldComplianceInd>
      <EmployeeCnt>0</EmployeeCnt>
      <UnrelatedBusIncmOverLimitInd>false</UnrelatedBusIncmOverLimitInd>
      <ForeignFinancialAccountInd>false</ForeignFinancialAccountInd>
      <ProhibitedTaxShelterTransInd>false</ProhibitedTaxShelterTransInd>
      <TaxablePartyNotificationInd>false</TaxablePartyNotificationInd>
      <NondeductibleContributionsInd>false</NondeductibleContributionsInd>
      <IndoorTanningServicesInd>false</IndoorTanningServicesInd>
      <SubjToTaxRmnrtnExPrchtPymtInd>false</SubjToTaxRmnrtnExPrchtPymtInd>
      <SubjectToExcsTaxNetInvstIncInd>false</SubjectToExcsTaxNetInvstIncInd>
      <InfoInScheduleOPartVIInd>X</InfoInScheduleOPartVIInd>
      <GoverningBodyVotingMembersCnt>4</GoverningBodyVotingMembersCnt>
      <IndependentVotingMemberCnt>4</IndependentVotingMemberCnt>
      <FamilyOrBusinessRlnInd>false</FamilyOrBusinessRlnInd>
      <DelegationOfMgmtDutiesInd>true</DelegationOfMgmtDutiesInd>
      <ChangeToOrgDocumentsInd>false</ChangeToOrgDocumentsInd>
      <MaterialDiversionOrMisuseInd>false</MaterialDiversionOrMisuseInd>
      <MembersOrStockholdersInd>false</MembersOrStockholdersInd>
      <ElectionOfBoardMembersInd>false</ElectionOfBoardMembersInd>
      <DecisionsSubjectToApprovaInd>false</DecisionsSubjectToApprovaInd>
      <MinutesOfGoverningBodyInd>true</MinutesOfGoverningBodyInd>
      <MinutesOfCommitteesInd>false</MinutesOfCommitteesInd>
      <OfficerMailingAddressInd>false</OfficerMailingAddressInd>
      <LocalChaptersInd>false</LocalChaptersInd>
      <Form990ProvidedToGvrnBodyInd>true</Form990ProvidedToGvrnBodyInd>
      <ConflictOfInterestPolicyInd>true</ConflictOfInterestPolicyInd>
      <AnnualDisclosureCoveredPrsnInd>true</AnnualDisclosureCoveredPrsnInd>
      <RegularMonitoringEnfrcInd>true</RegularMonitoringEnfrcInd>
      <WhistleblowerPolicyInd>true</WhistleblowerPolicyInd>
      <DocumentRetentionPolicyInd>false</DocumentRetentionPolicyInd>
      <CompensationProcessCEOInd>false</CompensationProcessCEOInd>
      <CompensationProcessOtherInd>false</CompensationProcessOtherInd>
      <InvestmentInJointVentureInd>false</InvestmentInJointVentureInd>
      <StatesWhereCopyOfReturnIsFldCd>CA</StatesWhereCopyOfReturnIsFldCd>
      <UponRequestInd>X</UponRequestInd>
      <BooksInCareOfDetail>
        <PersonNm>UNION ROOFERS ADMIN FUND</PersonNm>
        <PhoneNum>5629271434</PhoneNum>
        <USAddress>
          <AddressLine1Txt>9901 PARAMOUNT BVD 221</AddressLine1Txt>
          <CityNm>DOWNEY</CityNm>
          <StateAbbreviationCd>CA</StateAbbreviationCd>
          <ZIPCd>90240</ZIPCd>
        </USAddress>
      </BooksInCareOfDetail>
      <Form990PartVIISectionAGrp>
        <PersonNm>SUE PERILLO</PersonNm>
        <TitleTxt>FUND MANAGER</TitleTxt>
        <AverageHoursPerWeekRt>1.00</AverageHoursPerWeekRt>
        <AverageHoursPerWeekRltdOrgRt>40.00</AverageHoursPerWeekRltdOrgRt>
        <OfficerInd>X</OfficerInd>
        <ReportableCompFromOrgAmt>0</ReportableCompFromOrgAmt>
        <ReportableCompFromRltdOrgAmt>92133</ReportableCompFromRltdOrgAmt>
        <OtherCompensationAmt>36474</OtherCompensationAmt>
      </Form990PartVIISectionAGrp>
      <Form990PartVIISectionAGrp>
        <PersonNm>BRENT BEASLEY</PersonNm>
        <TitleTxt>Chairman</TitleTxt>
        <AverageHoursPerWeekRt>1.00</AverageHoursPerWeekRt>
        <AverageHoursPerWeekRltdOrgRt>0.00</AverageHoursPerWeekRltdOrgRt>
        <IndividualTrusteeOrDirectorInd>X</IndividualTrusteeOrDirectorInd>
        <OfficerInd>X</OfficerInd>
        <ReportableCompFromOrgAmt>0</ReportableCompFromOrgAmt>
        <ReportableCompFromRltdOrgAmt>0</ReportableCompFromRltdOrgAmt>
        <OtherCompensationAmt>0</OtherCompensationAmt>
      </Form990PartVIISectionAGrp>
      <Form990PartVIISectionAGrp>
        <PersonNm>ERNEST GLASGO</PersonNm>
        <TitleTxt>CO-CHAIRMAN</TitleTxt>
        <AverageHoursPerWeekRt>1.00</AverageHoursPerWeekRt>
        <AverageHoursPerWeekRltdOrgRt>0.00</AverageHoursPerWeekRltdOrgRt>
        <IndividualTrusteeOrDirectorInd>X</IndividualTrusteeOrDirectorInd>
        <OfficerInd>X</OfficerInd>
        <ReportableCompFromOrgAmt>0</ReportableCompFromOrgAmt>
        <ReportableCompFromRltdOrgAmt>0</ReportableCompFromRltdOrgAmt>
        <OtherCompensationAmt>0</OtherCompensationAmt>
      </Form990PartVIISectionAGrp>
      <Form990PartVIISectionAGrp>
        <PersonNm>CLIFFORD SMITH</PersonNm>
        <TitleTxt>Trustee</TitleTxt>
        <AverageHoursPerWeekRt>1.00</AverageHoursPerWeekRt>
        <AverageHoursPerWeekRltdOrgRt>0.00</AverageHoursPerWeekRltdOrgRt>
        <IndividualTrusteeOrDirectorInd>X</IndividualTrusteeOrDirectorInd>
        <ReportableCompFromOrgAmt>0</ReportableCompFromOrgAmt>
        <ReportableCompFromRltdOrgAmt>0</ReportableCompFromRltdOrgAmt>
        <OtherCompensationAmt>0</OtherCompensationAmt>
      </Form990PartVIISectionAGrp>
      <Form990PartVIISectionAGrp>
        <PersonNm>GREG BANKS</PersonNm>
        <TitleTxt>Trustee</TitleTxt>
        <AverageHoursPerWeekRt>1.00</AverageHoursPerWeekRt>
        <AverageHoursPerWeekRltdOrgRt>0.00</AverageHoursPerWeekRltdOrgRt>
        <IndividualTrusteeOrDirectorInd>X</IndividualTrusteeOrDirectorInd>
        <ReportableCompFromOrgAmt>0</ReportableCompFromOrgAmt>
        <ReportableCompFromRltdOrgAmt>0</ReportableCompFromRltdOrgAmt>
        <OtherCompensationAmt>0</OtherCompensationAmt>
      </Form990PartVIISectionAGrp>
      <TotReportableCompRltdOrgAmt>92133</TotReportableCompRltdOrgAmt>
      <TotalOtherCompensationAmt>36474</TotalOtherCompensationAmt>
      <IndivRcvdGreaterThan100KCnt>0</IndivRcvdGreaterThan100KCnt>
      <FormerOfcrEmployeesListedInd>false</FormerOfcrEmployeesListedInd>
      <TotalCompGreaterThan150KInd>false</TotalCompGreaterThan150KInd>
      <CompensationFromOtherSrcsInd>false</CompensationFromOtherSrcsInd>
      <CntrctRcvdGreaterThan100KCnt>0</CntrctRcvdGreaterThan100KCnt>
      <TotalContributionsAmt>0</TotalContributionsAmt>
      <ProgramServiceRevenueGrp>
        <Desc>EMPLOYER CONTRIBUTIONS</Desc>
        <BusinessCd>900099</BusinessCd>
        <TotalRevenueColumnAmt>6008245</TotalRevenueColumnAmt>
        <RelatedOrExemptFuncIncomeAmt>6008245</RelatedOrExemptFuncIncomeAmt>
      </ProgramServiceRevenueGrp>
      <ProgramServiceRevenueGrp>
        <Desc>FORFEITURES</Desc>
        <BusinessCd>900099</BusinessCd>
        <TotalRevenueColumnAmt>29115</TotalRevenueColumnAmt>
        <RelatedOrExemptFuncIncomeAmt>29115</RelatedOrExemptFuncIncomeAmt>
      </ProgramServiceRevenueGrp>
      <TotalProgramServiceRevenueAmt>6037360</TotalProgramServiceRevenueAmt>
      <InvestmentIncomeGrp>
        <TotalRevenueColumnAmt>883</TotalRevenueColumnAmt>
        <ExclusionAmt>883</ExclusionAmt>
      </InvestmentIncomeGrp>
      <IncmFromInvestBondProceedsGrp>
        <TotalRevenueColumnAmt>0</TotalRevenueColumnAmt>
      </IncmFromInvestBondProceedsGrp>
      <RoyaltiesRevenueGrp>
        <TotalRevenueColumnAmt>0</TotalRevenueColumnAmt>
      </RoyaltiesRevenueGrp>
      <NetRentalIncomeOrLossGrp>
        <TotalRevenueColumnAmt>0</TotalRevenueColumnAmt>
      </NetRentalIncomeOrLossGrp>
      <NetGainOrLossInvestmentsGrp>
        <TotalRevenueColumnAmt>0</TotalRevenueColumnAmt>
      </NetGainOrLossInvestmentsGrp>
      <NetIncmFromFundraisingEvtGrp>
        <TotalRevenueColumnAmt>0</TotalRevenueColumnAmt>
      </NetIncmFromFundraisingEvtGrp>
      <NetIncomeFromGamingGrp>
        <TotalRevenueColumnAmt>0</TotalRevenueColumnAmt>
      </NetIncomeFromGamingGrp>
      <NetIncomeOrLossGrp>
        <TotalRevenueColumnAmt>0</TotalRevenueColumnAmt>
      </NetIncomeOrLossGrp>
      <OtherRevenueMiscGrp>
        <Desc>OTHER INCOME</Desc>
        <BusinessCd>900099</BusinessCd>
        <TotalRevenueColumnAmt>1171</TotalRevenueColumnAmt>
        <RelatedOrExemptFuncIncomeAmt>1171</RelatedOrExemptFuncIncomeAmt>
      </OtherRevenueMiscGrp>
      <OtherRevenueTotalAmt>1171</OtherRevenueTotalAmt>
      <TotalRevenueGrp>
        <TotalRevenueColumnAmt>6039414</TotalRevenueColumnAmt>
        <RelatedOrExemptFuncIncomeAmt>6038531</RelatedOrExemptFuncIncomeAmt>
        <ExclusionAmt>883</ExclusionAmt>
      </TotalRevenueGrp>
      <GrantsToDomesticOrgsGrp>
        <TotalAmt>0</TotalAmt>
      </GrantsToDomesticOrgsGrp>
      <GrantsToDomesticIndividualsGrp>
        <TotalAmt>0</TotalAmt>
      </GrantsToDomesticIndividualsGrp>
      <ForeignGrantsGrp>
        <TotalAmt>0</TotalAmt>
      </ForeignGrantsGrp>
      <BenefitsToMembersGrp>
        <TotalAmt>6008245</TotalAmt>
      </BenefitsToMembersGrp>
      <CompCurrentOfcrDirectorsGrp>
        <TotalAmt>0</TotalAmt>
      </CompCurrentOfcrDirectorsGrp>
      <CompDisqualPersonsGrp>
        <TotalAmt>0</TotalAmt>
      </CompDisqualPersonsGrp>
      <OtherSalariesAndWagesGrp>
        <TotalAmt>0</TotalAmt>
      </OtherSalariesAndWagesGrp>
      <PensionPlanContributionsGrp>
        <TotalAmt>0</TotalAmt>
      </PensionPlanContributionsGrp>
      <OtherEmployeeBenefitsGrp>
        <TotalAmt>0</TotalAmt>
      </OtherEmployeeBenefitsGrp>
      <PayrollTaxesGrp>
        <TotalAmt>0</TotalAmt>
      </PayrollTaxesGrp>
      <FeesForServicesManagementGrp>
        <TotalAmt>0</TotalAmt>
      </FeesForServicesManagementGrp>
      <FeesForServicesLegalGrp>
        <TotalAmt>675</TotalAmt>
      </FeesForServicesLegalGrp>
      <FeesForServicesAccountingGrp>
        <TotalAmt>4854</TotalAmt>
      </FeesForServicesAccountingGrp>
      <FeesForServicesLobbyingGrp>
        <TotalAmt>0</TotalAmt>
      </FeesForServicesLobbyingGrp>
      <FeesForServicesProfFundraising>
        <TotalAmt>0</TotalAmt>
      </FeesForServicesProfFundraising>
      <FeesForSrvcInvstMgmntFeesGrp>
        <TotalAmt>0</TotalAmt>
      </FeesForSrvcInvstMgmntFeesGrp>
      <FeesForServicesOtherGrp>
        <TotalAmt>10075</TotalAmt>
      </FeesForServicesOtherGrp>
      <AdvertisingGrp>
        <TotalAmt>0</TotalAmt>
      </AdvertisingGrp>
      <OfficeExpensesGrp>
        <TotalAmt>4505</TotalAmt>
      </OfficeExpensesGrp>
      <InformationTechnologyGrp>
        <TotalAmt>0</TotalAmt>
      </InformationTechnologyGrp>
      <RoyaltiesGrp>
        <TotalAmt>0</TotalAmt>
      </RoyaltiesGrp>
      <OccupancyGrp>
        <TotalAmt>0</TotalAmt>
      </OccupancyGrp>
      <TravelGrp>
        <TotalAmt>0</TotalAmt>
      </TravelGrp>
      <PymtTravelEntrtnmntPubOfclGrp>
        <TotalAmt>0</TotalAmt>
      </PymtTravelEntrtnmntPubOfclGrp>
      <ConferencesMeetingsGrp>
        <TotalAmt>0</TotalAmt>
      </ConferencesMeetingsGrp>
      <InterestGrp>
        <TotalAmt>0</TotalAmt>
      </InterestGrp>
      <PaymentsToAffiliatesGrp>
        <TotalAmt>0</TotalAmt>
      </PaymentsToAffiliatesGrp>
      <DepreciationDepletionGrp>
        <TotalAmt>0</TotalAmt>
      </DepreciationDepletionGrp>
      <InsuranceGrp>
        <TotalAmt>299</TotalAmt>
      </InsuranceGrp>
      <OtherExpensesGrp>
        <Desc>Expenses paid to related funds</Desc>
        <TotalAmt>25263</TotalAmt>
      </OtherExpensesGrp>
      <OtherExpensesGrp>
        <Desc>Bank Charges</Desc>
        <TotalAmt>9610</TotalAmt>
      </OtherExpensesGrp>
      <OtherExpensesGrp>
        <Desc>Custodial fees</Desc>
        <TotalAmt>2086</TotalAmt>
      </OtherExpensesGrp>
      <OtherExpensesGrp>
        <Desc>Postage and Shipping</Desc>
        <TotalAmt>555</TotalAmt>
      </OtherExpensesGrp>
      <AllOtherExpensesGrp>
        <TotalAmt>559</TotalAmt>
      </AllOtherExpensesGrp>
      <TotalFunctionalExpensesGrp>
        <TotalAmt>6066726</TotalAmt>
        <ProgramServicesAmt>0</ProgramServicesAmt>
        <ManagementAndGeneralAmt>0</ManagementAndGeneralAmt>
        <FundraisingAmt>0</FundraisingAmt>
      </TotalFunctionalExpensesGrp>
      <CashNonInterestBearingGrp>
        <BOYAmt>285135</BOYAmt>
        <EOYAmt>31138</EOYAmt>
      </CashNonInterestBearingGrp>
      <SavingsAndTempCashInvstGrp>
        <BOYAmt>4932</BOYAmt>
        <EOYAmt>1995733</EOYAmt>
      </SavingsAndTempCashInvstGrp>
      <PledgesAndGrantsReceivableGrp>
        <EOYAmt>0</EOYAmt>
      </PledgesAndGrantsReceivableGrp>
      <AccountsReceivableGrp>
        <BOYAmt>607370</BOYAmt>
        <EOYAmt>488924</EOYAmt>
      </AccountsReceivableGrp>
      <ReceivablesFromOfficersEtcGrp>
        <EOYAmt>0</EOYAmt>
      </ReceivablesFromOfficersEtcGrp>
      <RcvblFromDisqualifiedPrsnGrp>
        <EOYAmt>0</EOYAmt>
      </RcvblFromDisqualifiedPrsnGrp>
      <OthNotesLoansReceivableNetGrp>
        <EOYAmt>0</EOYAmt>
      </OthNotesLoansReceivableNetGrp>
      <InventoriesForSaleOrUseGrp>
        <EOYAmt>0</EOYAmt>
      </InventoriesForSaleOrUseGrp>
      <PrepaidExpensesDefrdChargesGrp>
        <EOYAmt>237</EOYAmt>
      </PrepaidExpensesDefrdChargesGrp>
      <LandBldgEquipBasisNetGrp>
        <EOYAmt>0</EOYAmt>
      </LandBldgEquipBasisNetGrp>
      <InvestmentsPubTradedSecGrp>
        <BOYAmt>1982245</BOYAmt>
        <EOYAmt>0</EOYAmt>
      </InvestmentsPubTradedSecGrp>
      <InvestmentsOtherSecuritiesGrp>
        <EOYAmt>0</EOYAmt>
      </InvestmentsOtherSecuritiesGrp>
      <InvestmentsProgramRelatedGrp>
        <EOYAmt>0</EOYAmt>
      </InvestmentsProgramRelatedGrp>
      <IntangibleAssetsGrp>
        <EOYAmt>0</EOYAmt>
      </IntangibleAssetsGrp>
      <OtherAssetsTotalGrp>
        <EOYAmt>0</EOYAmt>
      </OtherAssetsTotalGrp>
      <TotalAssetsGrp>
        <BOYAmt>2879682</BOYAmt>
        <EOYAmt>2516032</EOYAmt>
      </TotalAssetsGrp>
      <AccountsPayableAccrExpnssGrp>
        <EOYAmt>832</EOYAmt>
      </AccountsPayableAccrExpnssGrp>
      <OtherLiabilitiesGrp>
        <BOYAmt>2566236</BOYAmt>
        <EOYAmt>2233903</EOYAmt>
      </OtherLiabilitiesGrp>
      <TotalLiabilitiesGrp>
        <BOYAmt>2566236</BOYAmt>
        <EOYAmt>2234735</EOYAmt>
      </TotalLiabilitiesGrp>
      <OrgDoesNotFollowFASB117Ind>X</OrgDoesNotFollowFASB117Ind>
      <RtnEarnEndowmentIncmOthFndsGrp>
        <BOYAmt>313446</BOYAmt>
        <EOYAmt>281297</EOYAmt>
      </RtnEarnEndowmentIncmOthFndsGrp>
      <TotalNetAssetsFundBalanceGrp>
        <BOYAmt>313446</BOYAmt>
        <EOYAmt>281297</EOYAmt>
      </TotalNetAssetsFundBalanceGrp>
      <TotLiabNetAssetsFundBalanceGrp>
        <BOYAmt>2879682</BOYAmt>
        <EOYAmt>2516032</EOYAmt>
      </TotLiabNetAssetsFundBalanceGrp>
      <InfoInScheduleOPartXIInd>X</InfoInScheduleOPartXIInd>
      <ReconcilationRevenueExpnssAmt>-27312</ReconcilationRevenueExpnssAmt>
      <OtherChangesInNetAssetsAmt>-4837</OtherChangesInNetAssetsAmt>
      <MethodOfAccountingAccrualInd>X</MethodOfAccountingAccrualInd>
      <AccountantCompileOrReviewInd>false</AccountantCompileOrReviewInd>
      <FSAuditedInd>true</FSAuditedInd>
      <FSAuditedBasisGrp>
        <SeparateBasisFinclStmtInd>X</SeparateBasisFinclStmtInd>
      </FSAuditedBasisGrp>
      <AuditCommitteeInd>false</AuditCommitteeInd>
      <FederalGrantAuditRequiredInd>false</FederalGrantAuditRequiredInd>
    </IRS990>
    <IRS990ScheduleD documentId="IRS990ScheduleD" softwareId="20011551" softwareVersionNum="2020v4.0">
      <OtherLiabilitiesOrgGrp>
        <Desc>DUE TO RELATED Funds</Desc>
        <Amt>17596</Amt>
      </OtherLiabilitiesOrgGrp>
      <OtherLiabilitiesOrgGrp>
        <Desc>UNCLAIMED BENEFITS PAYABLE</Desc>
        <Amt>176935</Amt>
      </OtherLiabilitiesOrgGrp>
      <OtherLiabilitiesOrgGrp>
        <Desc>VACATION BENFITS PAYABLE</Desc>
        <Amt>2039372</Amt>
      </OtherLiabilitiesOrgGrp>
      <TotalLiabilityAmt>2233903</TotalLiabilityAmt>
      <FootnoteTextInd>X</FootnoteTextInd>
      <TotalRevEtcAuditedFinclStmtAmt>6039414</TotalRevEtcAuditedFinclStmtAmt>
      <RevenueSubtotalAmt>6039414</RevenueSubtotalAmt>
      <TotalRevenuePerForm990Amt>6039414</TotalRevenuePerForm990Amt>
      <TotExpnsEtcAuditedFinclStmtAmt>6066726</TotExpnsEtcAuditedFinclStmtAmt>
      <ExpensesSubtotalAmt>6066726</ExpensesSubtotalAmt>
      <TotalExpensesPerForm990Amt>6066726</TotalExpensesPerForm990Amt>
      <SupplementalInformationDetail>
        <FormAndLineReferenceDesc>Part X : FIN48 Footnote</FormAndLineReferenceDesc>
        <ExplanationTxt>Accounting principles generally accepted in the United States of America require Plan management to evaluate tax positions taken by the Plan and recognize a tax liability (or asset) if it has taken an uncertain position that more likely than not would not be sustained upon examination by the Internal Revenue Service. The Plan is subject to routine audits by taxing jurisdictions; however, there are currently no audits for any tax periods in progress.</ExplanationTxt>
      </SupplementalInformationDetail>
    </IRS990ScheduleD>
    <IRS990ScheduleO documentId="IRS990ScheduleO" softwareId="20011551" softwareVersionNum="2020v4.0">
      <SupplementalInformationDetail>
        <FormAndLineReferenceDesc>Form 990, Part VI, Line 3: Description of Delegated Duties to Management Company</FormAndLineReferenceDesc>
        <ExplanationTxt>THE ORGANIZATION'S MANAGEMENT DUTIES, INCLUDING THE ACCOUNTING FUNCTIONS AND PAYMENTS OF VACATION BENEFITS TO THE MEMBERS ARE PERFORMED THROUGH THE UNION ROOFERS ADMINISTRATIVE FUND.</ExplanationTxt>
      </SupplementalInformationDetail>
      <SupplementalInformationDetail>
        <FormAndLineReferenceDesc>Form 990, Part VI, Line 8: Explanation of No Contemporaneously Documentation of Meetings</FormAndLineReferenceDesc>
        <ExplanationTxt>THERE ARE NO COMMITTEES WITH THE AUTHORITY TO ACT ON BEHALF OF THE BOARD.</ExplanationTxt>
      </SupplementalInformationDetail>
      <SupplementalInformationDetail>
        <FormAndLineReferenceDesc>Form 990, Part VI, Line 11b: Form 990 Review Process</FormAndLineReferenceDesc>
        <ExplanationTxt>THE FORM 990 IS REVIEWED BY THE BOARD OF TRUSTEES, WITH ASSISTANCE FROM THE FUND'S AUDITOR. ALSO A COPY IS PROVIDED TO THE CHAIRMAN AND COCHAIRMAN.</ExplanationTxt>
      </SupplementalInformationDetail>
      <SupplementalInformationDetail>
        <FormAndLineReferenceDesc>Form 990, Part VI, Line 12c: Explanation of Monitoring and Enforcement of Conflicts</FormAndLineReferenceDesc>
        <ExplanationTxt>AS REQUIRED UNDER ERISA, THE TRUSTEES EVALUATE AND MONITOR POTENTIAL CONFLICTS IN THEIR RETENTION AND DEALINGS WITH SERVICE PROVIDERS AND OTHER PARTIES IN INTEREST AND AS OTHER CIRCUMSTANCES WARRANT. TRUSTEES ARE EXPECTED TO RECUSE THEMSELVES FROM DELIBERATIONS WHEN AN UNAVOIDABLE CONFLICT EXIST.</ExplanationTxt>
      </SupplementalInformationDetail>
      <SupplementalInformationDetail>
        <FormAndLineReferenceDesc>Form 990, Part VI, Line 19: Other Organization Documents Publicly Available</FormAndLineReferenceDesc>
        <ExplanationTxt>THE DOCUMENTS ARE AVAILABLE AT THE TRUST OFFICE FOR REVIEW BY THE PUBLIC.</ExplanationTxt>
      </SupplementalInformationDetail>
      <SupplementalInformationDetail>
        <FormAndLineReferenceDesc>Other Changes In Net Assets Or Fund Balances - Other Decreases</FormAndLineReferenceDesc>
        <ExplanationTxt>Adjustment for prior year Form 990 = -$4837</ExplanationTxt>
      </SupplementalInformationDetail>
      <SupplementalInformationDetail>
        <FormAndLineReferenceDesc>FORM 990 PART VII</FormAndLineReferenceDesc>
        <ExplanationTxt>TRUSTEES OF THE TRUST ARE EMPLOYEES OF CONTRIBUTING EMPLOYERS THAT ARE CONSIDERED RELATED ORGANIZATIONS UNDER THE DEFINITIONS IN SCHEDULE R. THE RELATED ORGANIZATIONS ARE FORPROFIT ORGANIZATIONS, ARE NOT OWNED OR CONTROLLED, DIRECTLY OR INDIRECTLY, BY THE ORGANIZATION OR ONE OR MORE RELATED TAXEXEMPT ORGANIZATIONS, AND DO NOT PROVIDE MANAGEMENT SERVICES FOR A FEE TO THE ORGANIZATION. AS SUCH COMPENSATION PAID BY RELATED ORGANIZATIONS IS NOT SHOWN UNDER THE VOLUNTEER EXCEPTION.</ExplanationTxt>
      </SupplementalInformationDetail>
    </IRS990ScheduleO>
    <IRS990ScheduleR documentId="IRS990ScheduleR" softwareId="20011551" softwareVersionNum="2020v4.0">
      <IdRelatedTaxExemptOrgGrp>
        <DisregardedEntityName>
          <BusinessNameLine1Txt>UNION ROOFERS ADMINSTRATIVE FUND</BusinessNameLine1Txt>
        </DisregardedEntityName>
        <USAddress>
          <AddressLine1Txt>9901 PARAMOUNT BVLD 211</AddressLine1Txt>
          <CityNm>DOWNEY</CityNm>
          <StateAbbreviationCd>CA</StateAbbreviationCd>
          <ZIPCd>99240</ZIPCd>
        </USAddress>
        <EIN>952159333</EIN>
        <PrimaryActivitiesTxt>PROVIDE ADMIN SERVICES TO RELATED FUNDS</PrimaryActivitiesTxt>
        <LegalDomicileStateCd>CA</LegalDomicileStateCd>
        <ExemptCodeSectionTxt>501(C)(9)</ExemptCodeSectionTxt>
        <DirectControllingNACd>N/A</DirectControllingNACd>
        <ControlledOrganizationInd>false</ControlledOrganizationInd>
      </IdRelatedTaxExemptOrgGrp>
      <IdRelatedTaxExemptOrgGrp>
        <DisregardedEntityName>
          <BusinessNameLine1Txt>UNION ROOFERS HEALTH &amp; WELFARE FUND</BusinessNameLine1Txt>
        </DisregardedEntityName>
        <USAddress>
          <AddressLine1Txt>9901 PARAMOUNT BLVD 211</AddressLine1Txt>
          <CityNm>DOWNEY</CityNm>
          <StateAbbreviationCd>CA</StateAbbreviationCd>
          <ZIPCd>90240</ZIPCd>
        </USAddress>
        <EIN>951856197</EIN>
        <PrimaryActivitiesTxt>PROVIDE HOSPITAL-MEDICAL BENEFITS</PrimaryActivitiesTxt>
        <LegalDomicileStateCd>CA</LegalDomicileStateCd>
        <ExemptCodeSectionTxt>501(C)(9)</ExemptCodeSectionTxt>
        <DirectControllingNACd>N/A</DirectControllingNACd>
        <ControlledOrganizationInd>false</ControlledOrganizationInd>
      </IdRelatedTaxExemptOrgGrp>
      <IdRelatedTaxExemptOrgGrp>
        <DisregardedEntityName>
          <BusinessNameLine1Txt>UNION ROOFERS JOINT APPREN TRAINING</BusinessNameLine1Txt>
        </DisregardedEntityName>
        <USAddress>
          <AddressLine1Txt>9901 PARAMOUNT BLVD 211</AddressLine1Txt>
          <CityNm>DOWNEY</CityNm>
          <StateAbbreviationCd>CA</StateAbbreviationCd>
          <ZIPCd>99204</ZIPCd>
        </USAddress>
        <EIN>952505044</EIN>
        <PrimaryActivitiesTxt>PROVIDE TRAINING IN ROOFING INDUSTRY</PrimaryActivitiesTxt>
        <LegalDomicileStateCd>CA</LegalDomicileStateCd>
        <ExemptCodeSectionTxt>501(C)(5)</ExemptCodeSectionTxt>
        <DirectControllingNACd>N/A</DirectControllingNACd>
        <ControlledOrganizationInd>false</ControlledOrganizationInd>
      </IdRelatedTaxExemptOrgGrp>
      <IdRelatedTaxExemptOrgGrp>
        <DisregardedEntityName>
          <BusinessNameLine1Txt>UNION ROOFERS ANNUITY FUND</BusinessNameLine1Txt>
        </DisregardedEntityName>
        <USAddress>
          <AddressLine1Txt>9901 PARAMOUNT BLVD SUITE 211</AddressLine1Txt>
          <CityNm>DOWNEY</CityNm>
          <StateAbbreviationCd>CA</StateAbbreviationCd>
          <ZIPCd>90240</ZIPCd>
        </USAddress>
        <EIN>953070101</EIN>
        <PrimaryActivitiesTxt>PROVIDE ANNUITY BENEFITS</PrimaryActivitiesTxt>
        <LegalDomicileStateCd>CA</LegalDomicileStateCd>
        <ExemptCodeSectionTxt>401(A)</ExemptCodeSectionTxt>
        <DirectControllingNACd>N/A</DirectControllingNACd>
        <ControlledOrganizationInd>false</ControlledOrganizationInd>
      </IdRelatedTaxExemptOrgGrp>
      <IdRelatedTaxExemptOrgGrp>
        <DisregardedEntityName>
          <BusinessNameLine1Txt>UNITED UNION OF ROOFERS LOCAL 36</BusinessNameLine1Txt>
        </DisregardedEntityName>
        <USAddress>
          <AddressLine1Txt>5380 POPLAR BLVD</AddressLine1Txt>
          <CityNm>LOS ANGELES</CityNm>
          <StateAbbreviationCd>CA</StateAbbreviationCd>
          <ZIPCd>90032</ZIPCd>
        </USAddress>
        <EIN>951161330</EIN>
        <PrimaryActivitiesTxt>LABOR ORGANIZATION</PrimaryActivitiesTxt>
        <LegalDomicileStateCd>CA</LegalDomicileStateCd>
        <ExemptCodeSectionTxt>501(C)(5)</ExemptCodeSectionTxt>
        <DirectControllingNACd>N/A</DirectControllingNACd>
        <ControlledOrganizationInd>false</ControlledOrganizationInd>
      </IdRelatedTaxExemptOrgGrp>
      <IdRelatedTaxExemptOrgGrp>
        <DisregardedEntityName>
          <BusinessNameLine1Txt>UNITED UNION OF ROOFERS LOCAL 220</BusinessNameLine1Txt>
        </DisregardedEntityName>
        <USAddress>
          <AddressLine1Txt>283 N RAMPART STREET</AddressLine1Txt>
          <CityNm>ORANGE</CityNm>
          <StateAbbreviationCd>CA</StateAbbreviationCd>
          <ZIPCd>92868</ZIPCd>
        </USAddress>
        <EIN>952418440</EIN>
        <PrimaryActivitiesTxt>LABOR ORGANIZATION</PrimaryActivitiesTxt>
        <LegalDomicileStateCd>CA</LegalDomicileStateCd>
        <ExemptCodeSectionTxt>501(C)(5)</ExemptCodeSectionTxt>
        <DirectControllingNACd>N/A</DirectControllingNACd>
        <ControlledOrganizationInd>false</ControlledOrganizationInd>
      </IdRelatedTaxExemptOrgGrp>
      <IdRelatedOrgTxblCorpTrGrp>
        <RelatedOrganizationName>
          <BusinessNameLine1Txt>SEE ATTACHED LISTING</BusinessNameLine1Txt>
        </RelatedOrganizationName>
        <USAddress>
          <AddressLine1Txt>9901 PARAMOUNT BLVD 211</AddressLine1Txt>
          <CityNm>DOWNEY</CityNm>
          <StateAbbreviationCd>CA</StateAbbreviationCd>
          <ZIPCd>90240</ZIPCd>
        </USAddress>
        <PrimaryActivitiesTxt>CONTRACTOR</PrimaryActivitiesTxt>
        <LegalDomicileStateCd>CA</LegalDomicileStateCd>
        <DirectControllingNACd>N/A</DirectControllingNACd>
        <EntityTypeTxt>VARIOUS</EntityTypeTxt>
        <ControlledOrganizationInd>false</ControlledOrganizationInd>
      </IdRelatedOrgTxblCorpTrGrp>
      <ReceiptOfIntAnntsRntsRyltsInd>false</ReceiptOfIntAnntsRntsRyltsInd>
      <GiftGrntOrCapContriToOthOrgInd>false</GiftGrntOrCapContriToOthOrgInd>
      <GiftGrntCapContriFromOthOrgInd>false</GiftGrntCapContriFromOthOrgInd>
      <LoansOrGuaranteesToOtherOrgInd>false</LoansOrGuaranteesToOtherOrgInd>
      <LoansOrGuaranteesFromOthOrgInd>false</LoansOrGuaranteesFromOthOrgInd>
      <DivRelatedOrganizationInd>false</DivRelatedOrganizationInd>
      <AssetSaleToOtherOrgInd>false</AssetSaleToOtherOrgInd>
      <AssetPurchaseFromOtherOrgInd>false</AssetPurchaseFromOtherOrgInd>
      <AssetExchangeInd>false</AssetExchangeInd>
      <RentalOfFacilitiesToOthOrgInd>false</RentalOfFacilitiesToOthOrgInd>
      <RentalOfFcltsFromOthOrgInd>false</RentalOfFcltsFromOthOrgInd>
      <PerformOfServicesForOthOrgInd>false</PerformOfServicesForOthOrgInd>
      <PerformOfServicesByOtherOrgInd>false</PerformOfServicesByOtherOrgInd>
      <SharingOfFacilitiesInd>false</SharingOfFacilitiesInd>
      <PaidEmployeesSharingInd>false</PaidEmployeesSharingInd>
      <ReimbursementPaidToOtherOrgInd>true</ReimbursementPaidToOtherOrgInd>
      <ReimbursementPaidByOtherOrgInd>false</ReimbursementPaidByOtherOrgInd>
      <TransferToOtherOrgInd>false</TransferToOtherOrgInd>
      <TransferFromOtherOrgInd>false</TransferFromOtherOrgInd>
      <TransactionsRelatedOrgGrp>
        <OtherOrganizationName>
          <BusinessNameLine1Txt>UNION ROOFERS ADMINSTRATIVE FUND</BusinessNameLine1Txt>
        </OtherOrganizationName>
        <TransactionTypeTxt>p</TransactionTypeTxt>
        <InvolvedAmt>25263</InvolvedAmt>
        <MethodOfAmountDeterminationTxt>ALLOCATED COST</MethodOfAmountDeterminationTxt>
      </TransactionsRelatedOrgGrp>
    </IRS990ScheduleR>
  </ReturnData>
</Return>
